Workbook

Sheet Updated Financial Statements 
A1: Finance >>Profit & Loss IND (Standalone)>>Tata Steel Ltd(Curr. in ) | I1: Finance >>Balance Sheet IND (Standalone)>>Tata Steel Ltd(Curr. in ) | Q1: Finance >>Cash Flow (Standalone)>>Tata Steel Ltd(Curr. Rs in )
A2: Year | B2: 2017 | C2: 2018 | D2: 2019 | E2: 2020 | F2: 2021 | G2: 2022 | I2: Year | J2: 2017 | K2: 2018 | L2: 2019 | M2: 2020 | N2: 2021 | O2: 2022 | Q2: Year | R2: 201703 | S2: 201803 | T2: 201903 | U2: 202003 | V2: 202103 | W2: 202203
A3: Revenue From Operations | B3: 53260.96 | C3: 60519.37 | D3: 70610.92 | E3: 60435.97 | F3: 84132.92 | G3: 129021.35 | I3: ASSETS | Q3: Cash Flow Summary
A4: Less: Excise Duty | B4: 5267.94 | C4: 902.55 | D4: 0 | E4: 0 | F4: 0 | G4: 0 | I4: Non-Current Assets: | Q4: Cash and Cash Equivalents at Beginning of the year | R4: 974.68 | S4: 905.21 | T4: 4588.89 | U4: 544.85 | V4: 1717.25 | W4: 2221.31
A5: Revenue From Operations(Net) | B5: 47993.02 | C5: 59616.82 | D5: 70610.92 | E5: 60435.97 | F5: 84132.92 | G5: 129021.35 | I5: Fixed Assets | J5: 78731.11 | K5: 77402.35 | L5: 77018.31 | M5: 79480.43 | N5: 108051.56 | O5: 108832.39 | Q5: Net Cash from Operating Activities | R5: 11166.64 | S5: 11791.45 | T5: 15193.11 | U5: 13453.66 | V5: 37554.77 | W5: 41986.12
A6: Other Income | B6: 414.46 | C6: 763.66 | D6: 2405.08 | E6: 404.12 | F6: 755.11 | G6: 1452.02 | I6: Property, Plant and Equipment | J6: 71778.97 | K6: 70942.9 | L6: 70416.82 | M6: 66392.35 | N6: 90404.59 | O6: 87946.22 | Q6: Net Profit before Tax & Extraordinary Items | R6: 5356.93 | S6: 6638.25 | T6: 16227.25 | U6: 6610.98 | V6: 18609.84 | W6: 44090.65
A7: Total Revenue | B7: 48407.48 | C7: 60380.48 | D7: 73016 | E7: 60840.09 | F7: 84888.03 | G7: 130473.37 | I7: Capital Work in Progress | J7: 6125.35 | K7: 5641.5 | L7: 5686.02 | M7: 8070.41 | N7: 10499.49 | O7: 14159.32 | Q7: Depreciation | R7: 3541.55 | S7: 3727.46 | T7: 3802.96 | U7: 3920.12 | V7: 5469.26 | W7: 5463.69
A8: EXPENSES: | I8: Intangible Assets | J8: 788.18 | K8: 786.18 | L8: 805.2 | M8: 727.72 | N8: 855.73 | O8: 806.03 | Q8: Interest (Net) | R8: 2290.69 | S8: 2022.24 | T8: 550.28 | U8: 2859.43 | V8: 4001.89 | W8: 1666.51
A9: Cost of Material Consumed | B9: 12496.78 | C9: 16877.63 | D9: 19840.29 | E9: 17407.03 | F9: 20757.04 | G9: 35256.98 | I9: Intangible Assets under Development | J9: 38.61 | K9: 31.77 | L9: 110.27 | M9: 176.64 | N9: 408.79 | O9: 382.64 | Q9: Dividend Received | R9: 0 | S9: -88.57 | T9: -96.25 | U9: -89.73 | V9: -68.11 | W9: -243.92
A10: Internally Manufactured Intermediates or Components Consumed | B10: 0 | C10: 0 | D10: 0 | E10: 0 | F10: 0 | G10: 0 | I10: Fixed Assets Held For Sale | J10: 0 | K10: 0 | L10: 0 | M10: 0 | N10: 0 | O10: 0 | Q10: P/L on Sales of Assets | R10: 0 | S10: 40.48 | T10: 1.42 | U10: 1.2 | V10: -22.88 | W10: -17.28
A11: Purchases of Stock-in-Trade | B11: 881.18 | C11: 647.21 | D11: 1807.85 | E11: 1563.1 | F11: 1688.84 | G11: 4089.03 | I11: Lease Adjustment | J11: 0 | K11: 0 | L11: 0 | M11: 0 | N11: 0 | O11: 0 | Q11: P/L on Sales of Invest | R11: -0.97 | S11: 0 | T11: 0 | U11: 0 | V11: 0 | W11: 0
A12: Changes in Inventories of Finished Goods, Work-in-Progress and Stock-in-Trade | B12: -1329.65 | C12: 545.36 | D12: -554.33 | E12: -564.4 | F12: 2176.56 | G12: -1820.87 | I12: Biological Assets other than Bearer Plants | J12: 0 | K12: 0 | L12: 0 | M12: 0 | N12: 0 | O12: 0 | Q12: Prov. & W/O (Net) | R12: 0 | S12: 0 | T12: 0 | U12: 0 | V12: 0 | W12: 0
A13: Employee Benefits / Salaries & other Staff Cost | B13: 4605.13 | C13: 4828.85 | D13: 5131.06 | E13: 5036.62 | F13: 5741.94 | G13: 6365.8 | I13: Non-current Investments | Q13: P/L in Forex | R13: 15.47 | S13: -88.17 | T13: -1.27 | U13: -85.86 | V13: -20.33 | W13: -851.6
A14: Finance Cost | B14: 2688.55 | C14: 2810.62 | D14: 2823.58 | E14: 3031.01 | F14: 4541.02 | G14: 2792.08 | I14: Investment Properties | J14: 0 | K14: 0 | L14: 0 | M14: 0 | N14: 0 | O14: 0 | Q14: Fin. Lease & Rental Chrgs | R14: 0 | S14: 0 | T14: 0 | U14: 0 | V14: 0 | W14: 0
A15: Depreciation and Amortization | B15: 3541.55 | C15: 3727.46 | D15: 3802.96 | E15: 3920.12 | F15: 5469.26 | G15: 5463.69 | I15: Investments in Subsidiaries, Associates and Joint venture | J15: 3547.57 | K15: 8829.01 | L15: 38177.3 | M15: 46353.26 | N15: 28222.22 | O15: 41877.92 | Q15: Others | R15: 357.01 | S15: 2857.29 | T15: -535.51 | U15: 552.14 | V15: -742.47 | W15: 198.65
A16: Other Expenses | B16: 19463.63 | C16: 20938.81 | D16: 23823.11 | E16: 22132.05 | F16: 26644.83 | G16: 34000.56 | I16: Financial Assets : | Q16: Total Adjustments (PBT & Extraordinary Items) | R16: 6203.75 | S16: 8470.73 | T16: 3721.63 | U16: 7157.3 | V16: 8617.36 | W16: 6216.05
A17: Total Expenses | B17: 42347.17 | C17: 50375.94 | D17: 56674.52 | E17: 52525.53 | F17: 67019.49 | G17: 86147.27 | I17: Investments of Life Insurance Business | J17: 0 | K17: 0 | L17: 0 | M17: 0 | N17: 0 | O17: 0 | Q17: Op. Profit before Working Capital Changes | R17: 11560.68 | S17: 15108.98 | T17: 19948.88 | U17: 13768.28 | V17: 27227.2 | W17: 50306.7
A18: Profit Before Exceptional Items and Tax | B18: 6060.31 | C18: 10004.54 | D18: 16341.48 | E18: 8314.56 | F18: 17868.54 | G18: 44326.1 | I18: Investments - Long-term | J18: 4808.33 | K18: 807.55 | L18: 751.95 | M18: 507.65 | N18: 865.11 | O18: 1523.51 | Q18: Trade & 0th receivables | R18: 0 | S18: 0 | T18: 0 | U18: 0 | V18: 0 | W18: 0
A19: Exceptional Items Before Tax | B19: -703.38 | C19: -3366.29 | D19: -114.23 | E19: -1703.58 | F19: 741.3 | G19: -235.45 | I19: Loans - Long - Term | J19: 211.97 | K19: 213.5 | L19: 231.16 | M19: 199.26 | N19: 7570.1 | O19: 30195.27 | Q19: Inventories | R19: -3093.05 | S19: -784.63 | T19: -214.6 | U19: 533.21 | V19: 2664.03 | W19: -7072.78
A20: Profit Before Extraordinary Items and Tax | B20: 5356.93 | C20: 6638.25 | D20: 16227.25 | E20: 6610.98 | F20: 18609.84 | G20: 44090.65 | I20: Others Financial Assets - Long-term | J20: 79.61 | K20: 33.34 | L20: 319.7 | M20: 222.88 | N20: 384.19 | O20: 1345.02 | Q20: Trade Payables | R20: 0 | S20: 0 | T20: 0 | U20: 0 | V20: 0 | W20: 0
A21: Prior Year Adjustments | B21: 0 | C21: 0 | D21: 0 | E21: 0 | F21: 0 | G21: 0 | I21: Non Current Tax Assets - Long - Term | J21: 867.75 | K21: 1043.84 | L21: 1428.38 | M21: 1557.82 | N21: 3496.49 | O21: 3620.76 | Q21: Loans & Advances | R21: 0 | S21: 0 | T21: 0 | U21: 0 | V21: 0 | W21: 0
A22: Other Adjustments Before Tax | B22: 0 | C22: 0 | D22: 0 | E22: 0 | F22: 0 | G22: 0 | Q22: Investments | R22: 0 | S22: 0 | T22: 0 | U22: 0 | V22: 0 | W22: 0
A23: Extraordinary Items Before Tax | B23: 0 | C23: 0 | D23: 0 | E23: 0 | F23: 0 | G23: 0 | I23: Insurance Related Assets | J23: 0 | K23: 0 | L23: 0 | M23: 0 | N23: 0 | O23: 0 | Q23: Net Stock on Hire | R23: 0 | S23: 0 | T23: 0 | U23: 0 | V23: 0 | W23: 0
A24: Profit Before Tax | B24: 5356.93 | C24: 6638.25 | D24: 16227.25 | E24: 6610.98 | F24: 18609.84 | G24: 44090.65 | I24: Other Non-current Assets | J24: 3108.67 | K24: 2140.84 | L24: 2535.98 | M24: 2062.07 | N24: 2626.86 | O24: 3301.78 | Q24: Leased Assets Net of Sale | R24: 0 | S24: 0 | T24: 0 | U24: 0 | V24: 0 | W24: 0
A25: Tax Expenses | B25: 1912.38 | C25: 2468.7 | D25: 5694.06 | E25: -132.82 | F25: 1531.87 | G25: 11079.47 | I25: Deferred Tax Assets (Net) | J25: 0 | K25: 0 | L25: 0 | M25: 0 | N25: 0 | O25: 0 | Q25: Trade Bill(s) Purchased | R25: 0 | S25: 0 | T25: 0 | U25: 0 | V25: 0 | W25: 0
A26: Current Tax | B26: 1400.54 | C26: 1586.78 | D26: 6297.11 | E26: 1787.95 | F26: -1329.78 | G26: 11611.94 | I26: Total Reported Non-current Assets | J26: 91355.01 | K26: 90470.43 | L26: 120462.78 | M26: 130383.37 | N26: 151216.53 | O26: 190696.65 | Q26: Change in Borrowing | R26: 0 | S26: 0 | T26: 0 | U26: 0 | V26: 0 | W26: 0
A27: Deferred Tax | B27: 511.84 | C27: 881.92 | D27: -603.05 | E27: -1920.77 | F27: 2861.65 | G27: -532.47 | Q27: Change in Deposits | R27: 0 | S27: 0 | T27: 0 | U27: 0 | V27: 0 | W27: 0
A28: Other Tax Adjustments | B28: 0 | C28: 0 | D28: 0 | E28: 0 | F28: 0 | G28: 0 | I28: Current Assets: | Q28: Others | R28: 4239.88 | S28: -30.39 | T28: -8.63 | U28: 970.95 | V28: 8035.79 | W28: 9992.43
A29: Current Tax - MAT / MAT Credit Entitlement | B29: 0 | C29: 0 | D29: 0 | E29: 0 | F29: 0 | G29: 0 | Q29: Total (OP before Working Capital Changes) | R29: 1146.83 | S29: -815.02 | T29: -223.23 | U29: 1504.16 | V29: 10699.82 | W29: 2919.65
A30: Fringe Benefits Tax | B30: 0 | C30: 0 | D30: 0 | E30: 0 | F30: 0 | G30: 0 | I30: Inventories | J30: 10236.85 | K30: 11023.41 | L30: 11255.34 | M30: 10716.66 | N30: 12857.51 | O30: 19942.94 | Q30: Cash Generated from/(used in) Operations | R30: 12707.51 | S30: 14293.96 | T30: 19725.65 | U30: 15272.44 | V30: 37927.02 | W30: 53226.35
A31: Provision for Wealth Tax | B31: 0 | C31: 0 | D31: 0 | E31: 0 | F31: 0 | G31: 0 | I31: Biological Assets other than Bearer Plants | J31: 0 | K31: 0 | L31: 0 | M31: 0 | N31: 0 | O31: 0 | Q31: Interest Paid(Net) | R31: 0 | S31: 0 | T31: 0 | U31: 0 | V31: 0 | W31: 0
A32: Adjust for Previous Year | B32: 0 | C32: 0 | D32: 0 | E32: 0 | F32: 0 | G32: 0 | I32: Financial Assets : | Q32: Direct Taxes Paid | R32: -1540.87 | S32: -2502.51 | T32: -4532.54 | U32: -1818.78 | V32: -372.25 | W32: -11240.23
A33: Others | B33: 0 | C33: 0 | D33: 0 | E33: 0 | F33: 0 | G33: 0 | I33: Current Investments | J33: 5309.81 | K33: 14640.37 | L33: 477.47 | M33: 3235.16 | N33: 7096.8 | O33: 96.11 | Q33: Advance Tax Paid | R33: 0 | S33: 0 | T33: 0 | U33: 0 | V33: 0 | W33: 0
A34: Profit After Tax | B34: 3444.55 | C34: 4169.55 | D34: 10533.19 | E34: 6743.8 | F34: 17077.97 | G34: 33011.18 | I34: Trade Receivables | J34: 2006.52 | K34: 1875.63 | L34: 1363.04 | M34: 1016.73 | N34: 2878.58 | O34: 3280.3 | Q34: Others | R34: 0 | S34: 0 | T34: 0 | U34: 0 | V34: 0 | W34: 0
A35: Pre-acquisition Profit | B35: 0 | C35: 0 | D35: 0 | E35: 0 | F35: 0 | G35: 0 | I35: Cash and Cash Equivalents | J35: 905.21 | K35: 4588.89 | L35: 544.85 | M35: 993.64 | N35: 2221.31 | O35: 2671.59 | Q35: Total-others | R35: -1540.87 | S35: -2502.51 | T35: -4532.54 | U35: -1818.78 | V35: -372.25 | W35: -11240.23
A36: Profit After Pre-acquisition Profit | B36: 3444.55 | C36: 4169.55 | D36: 10533.19 | E36: 6743.8 | F36: 17077.97 | G36: 33011.18 | I36: Bank Balances Other Than Cash and Cash Equivalents | J36: 65.1 | K36: 107.85 | L36: 173.26 | M36: 233.23 | N36: 175.59 | O36: 183.7 | Q36: Cash Flow before Extraordinary Items | R36: 11166.64 | S36: 11791.45 | T36: 15193.11 | U36: 13453.66 | V36: 37554.77 | W36: 41986.12
A37: Extraordinary Items After Tax | B37: 0 | C37: 0 | D37: 0 | E37: 0 | F37: 0 | G37: 0 | I37: Loans - Short-term | J37: 27.14 | K37: 74.13 | L37: 55.92 | M37: 1607.32 | N37: 1564.37 | O37: 2368.01 | Q37: Excess Depreciation W/b | R37: 0 | S37: 0 | T37: 0 | U37: 0 | V37: 0 | W37: 0
A38: Profit/(Loss) for the period from Continuing Operations | B38: 3444.55 | C38: 4169.55 | D38: 10533.19 | E38: 6743.8 | F38: 17077.97 | G38: 33011.18 | I38: Others Financial Assets - Short-term | J38: 321.32 | K38: 521.58 | L38: 955.72 | M38: 440.37 | N38: 936.54 | O38: 786.33 | Q38: Premium on Lease of land | R38: 0 | S38: 0 | T38: 0 | U38: 0 | V38: 0 | W38: 0
A39: Discontinued Operations | B39: 0 | C39: 0 | D39: 0 | E39: 0 | F39: 0 | G39: 0 | I39: Current Tax Assets - Short-term | J39: 0 | K39: 0 | L39: 0 | M39: 0 | N39: 71.58 | O39: 0 | Q39: Payment Towards VRS | R39: 0 | S39: 0 | T39: 0 | U39: 0 | V39: 0 | W39: 0
A40: Profit / (Loss) from Discontinuing Operations | B40: 0 | C40: 0 | D40: 0 | E40: 0 | F40: 0 | G40: 0 | I40: Insurance Related Assets | J40: 0 | K40: 0 | L40: 0 | M40: 0 | N40: 0 | O40: 0 | Q40: Prior Year 's Taxation | R40: 0 | S40: 0 | T40: 0 | U40: 0 | V40: 0 | W40: 0
A41: Tax Expense of Discontinuing Operations | B41: 0 | C41: 0 | D41: 0 | E41: 0 | F41: 0 | G41: 0 | I41: Other Current Assets | J41: 1238.45 | K41: 1812.05 | L41: 2209.98 | M41: 1715.92 | N41: 1088.5 | O41: 1939.08 | Q41: Gain on Forex Exch. Tran | R41: 0 | S41: 0 | T41: 0 | U41: 0 | V41: 0 | W41: 0
A42: Accounting Changes | B42: 0 | C42: 0 | D42: 0 | E42: 0 | F42: 0 | G42: 0 | I42: Assets Classified as Held for Sale | J42: 0 | K42: 0 | L42: 0 | M42: 50.16 | N42: 383.62 | O42: 0 | Q42: Others | R42: 0 | S42: 0 | T42: 0 | U42: 0 | V42: 0 | W42: 0
A43: Profit Attributable to Shareholders | B43: 3444.55 | C43: 4169.55 | D43: 10533.19 | E43: 6743.8 | F43: 17077.97 | G43: 33011.18 | I43: Total Current Assets | J43: 20110.4 | K43: 34643.91 | L43: 17035.58 | M43: 20009.19 | N43: 29274.4 | O43: 31289.57 | Q43: Net Cash Used in Investing Activities | R43: -3956.4 | S43: -12273.35 | T43: -16349.98 | U43: -17634.66 | V43: -13665.22 | W43: -34167.79
A44: Adjustments to Net Income | B44: -174.01 | C44: -173.43 | D44: -173.13 | E44: -199.18 | F44: -181.35 | G44: -1.09 | Q44: Purchased of Fixed Assets | R44: -3212.72 | S44: -2527.46 | T44: -3676.86 | U44: -4749.28 | V44: -2266.22 | W44: -6288.29
A45: Interim Preference Dividend | B45: 0 | C45: 0 | D45: 0 | E45: 0 | F45: 0 | G45: 0 | I45: Foreign Currency Monetary Item Translation Difference Account | J45: 0 | K45: 0 | L45: 0 | M45: 0 | N45: 0 | O45: 0 | Q45: Sale of Fixed Assets | R45: 6.8 | S45: 13.28 | T45: 18.94 | U45: 173.07 | V45: 36.25 | W45: 132.61
A46: Proposed / Final Preference Dividend | B46: 0 | C46: 0 | D46: 0 | E46: 0 | F46: 0 | G46: 0 | Q46: Capital Expenditure | R46: 0 | S46: 0 | T46: 0 | U46: 0 | V46: 0 | W46: 0
A47: Prior Year Preference Dividend Paid | B47: 0 | C47: 0 | D47: 0 | E47: 0 | F47: 0 | G47: 0 | I47: Regulatory Deferral Account - Debit Balance | J47: 0 | K47: 0 | L47: 0 | M47: 0 | N47: 0 | O47: 0 | Q47: capital WIP | R47: 0 | S47: 0 | T47: 0 | U47: 0 | V47: 0 | W47: 0
A48: Preference Dividend | B48: 0 | C48: 0 | D48: 0 | E48: 0 | F48: 0 | G48: 0 | I48: Other Assets Excluding Non-Current and Current Assets | J48: 0 | K48: 0 | L48: 0 | M48: 0 | N48: 0 | O48: 0 | Q48: Capital Subsidy Recd | R48: 0 | S48: 0 | T48: 0 | U48: 0 | V48: 0 | W48: 0
A49: Preference Dividend Tax | B49: 0 | C49: 0 | D49: 0 | E49: 0 | F49: 0 | G49: 0 | Q49: Purchase of Investments | R49: -845.92 | S49: -8650.92 | T49: -403.02 | U49: -2722.7 | V49: -3694.91 | W49: -55.39
A50: Profit Attributable to Ordinary Shareholders | B50: 3270.54 | C50: 3996.12 | D50: 10360.06 | E50: 6544.62 | F50: 16896.62 | G50: 33010.09 | I50: Total Non-Current and Other Assets | J50: 91355.01 | K50: 90470.43 | L50: 120462.78 | M50: 130383.37 | N50: 151216.53 | O50: 190696.65 | Q50: Sale of Investments | R50: 3.9 | S50: 3877.78 | T50: 15066.32 | U50: 0 | V50: 0 | W50: 7193.3
A51: Others | B51: 0 | C51: 0 | D51: 0 | E51: 0 | F51: 0 | G51: 0 | Q51: Investment Income | R51: 0 | S51: 0 | T51: 0 | U51: 0 | V51: 0 | W51: 0
A52: Transfer from Reserves | B52: 0 | C52: 0 | D52: 0 | E52: 0 | F52: 0 | G52: 0 | I52: Total Assets | J52: 111465.41 | K52: 125114.34 | L52: 137498.36 | M52: 150392.56 | N52: 180490.93 | O52: 221986.22 | Q52: Interest Received | R52: 117.34 | S52: 92.67 | T52: 1696.86 | U52: 117.34 | V52: 260.86 | W52: 144.32
A53: Unappropriated Profits Brought Forward | B53: 0 | C53: 0 | D53: 0 | E53: 0 | F53: 0 | G53: 0 | Q53: Dividend Received | R53: 87.51 | S53: 88.57 | T53: 96.25 | U53: 89.73 | V53: 68.11 | W53: 243.92
A54: Profits Available for Appropriation | B54: 3270.54 | C54: 3996.12 | D54: 10360.06 | E54: 6544.62 | F54: 16896.62 | G54: 33010.09 | I54: EQUITY AND LIABILITIES | Q54: Invest.In Subsidiaires | R54: -100.12 | S54: -5018.88 | T54: -29076.49 | U54: -8945.16 | V54: -937.07 | W54: -12897
A55: Dividend | B55: 0 | C55: 0 | D55: 0 | E55: 0 | F55: 0 | G55: 0 | Q55: Loans to Subsidiaires | R55: 0 | S55: 0 | T55: 0 | U55: 0 | V55: 0 | W55: 0
A56: Transfer to Reserves | B56: 0 | C56: 0 | D56: 0 | E56: 0 | F56: 0 | G56: 0 | I56: Share Capital | J56: 971.41 | K56: 1146.12 | L56: 1146.12 | M56: 1146.13 | N56: 1198.78 | O56: 1222.37 | Q56: Investment in Group Cos | R56: 0 | S56: 0 | T56: 0 | U56: 0 | V56: 0 | W56: 0
A57: Dividend Tax | B57: 0 | C57: 0 | D57: 0 | E57: 0 | F57: 0 | G57: 0 | I57: Number of Equity Shares - Bought Back during the Current period | J57: 0 | K57: 0 | L57: 0 | M57: 0 | N57: 0 | O57: 0 | Q57: Issue of Sh. on Acqu. of Cos | R57: 0 | S57: 0 | T57: 0 | U57: 0 | V57: 0 | W57: 0
A58: Capitalization for Bonus Issue | B58: 0 | C58: 0 | D58: 0 | E58: 0 | F58: 0 | G58: 0 | I58: Number of Total Bonus Shares Issued upto Current period | J58: 25.79 | K58: 25.79 | L58: 25.79 | M58: 25.79 | N58: 25.79 | O58: 25.79 | Q58: Canc. of Invest. in Cos Acq. | R58: 0 | S58: 0 | T58: 0 | U58: 0 | V58: 21.06 | W58: 0
A59: Unappropriated Profits Carried Forward | B59: 3270.54 | C59: 3996.12 | D59: 10360.06 | E59: 6544.62 | F59: 16896.62 | G59: 33010.09 | I59: Number of Equity Shares - Paid Up | J59: 97.12 | K59: 120.41 | L59: 120.41 | M59: 120.41 | N59: 120.41 | O59: 122.23 | Q59: Acquisition of Companies | R59: 0 | S59: 0 | T59: 0 | U59: 0 | V59: 0 | W59: 0
A60: Other Comprehensive Income : | I60: Paid Up Capital | J60: 971.41 | K60: 1146.12 | L60: 1146.12 | M60: 1146.13 | N60: 1198.78 | O60: 1222.37 | Q60: Inter Corporate Deposits | R60: 0 | S60: 0 | T60: 0 | U60: 0 | V60: 0 | W60: 0
A61: Other Comprehensive Income That Will Not Be Reclassified to Profit Or Loss | B61: 676.59 | C61: -67.61 | D61: -43.31 | E61: -588.92 | F61: 390.79 | G61: 592.7 | I61: Treasury Shares | J61: 0 | K61: 0 | L61: 0 | M61: 0 | N61: 0 | O61: 0 | Q61: Others | R61: -13.19 | S61: -148.39 | T61: -71.98 | U61: -1597.66 | V61: -7153.3 | W61: -22641.26
A62: Other Comprehensive Income That Will Be Reclassified to Profit Or Loss : | B62: -0.8 | C62: 6.49 | D62: -6.91 | E62: -59.95 | F62: 20.62 | G62: 102.2 | I62: Number of Bonus Shares Issued During the Current Period. | J62: 0 | K62: 0 | L62: 0 | M62: 0 | N62: 0 | O62: 0 | Q62: Net Cash Used in Financing Activities | R62: -7279.71 | S62: 4165.58 | T62: -2887.17 | U62: 4629.79 | V62: -23385.49 | W62: -7368.05
A63: Other Comprehensive Income no Specification : | B63: 0 | C63: 0 | D63: 0 | E63: 0 | F63: 0 | G63: 0 | I63: Number of Shares Splitted During the Current Period. | J63: 0 | K63: 0 | L63: 0 | M63: 0 | N63: 0 | O63: 0 | Q63: Proceeds from Issue of shares (incl share premium) | R63: 0.01 | S63: 9087.23 | T63: 0 | U63: 0.04 | V63: 3240.91 | W63: 325.72
A64: Non-Controlling Interests | B64: 0 | C64: 0 | D64: 0 | E64: 0 | F64: 0 | G64: 0 | Q64: Proceed from Issue of Debentures | R64: 0 | S64: 0 | T64: 0 | U64: 0 | V64: 0 | W64: 0
A65: Total Comprehensive Income for the Year | B65: 4120.34 | C65: 4108.43 | D65: 10482.97 | E65: 6094.93 | F65: 17489.38 | G65: 33706.08 | I65: Other Equity | J65: 48687.59 | K65: 60368.7 | L65: 69308.59 | M65: 73416.99 | N65: 93207.56 | O65: 124211.39 | Q65: Proceed from 0ther Long Term Borrowings | R65: 0 | S65: 0 | T65: 5911.02 | U65: 5052.88 | V65: 9777.19 | W65: 36.88
A66: Earning Per Share - Basic | B66: 31.74 | C66: 38.57 | D66: 90.41 | E66: 57.11 | F66: 145 | G66: 270.33 | I66: Money Received Against Share Warrants | J66: 0 | K66: 0 | L66: 0 | M66: 0 | N66: 0 | O66: 0 | Q66: Proceed from Bank Borrowings | R66: 0 | S66: 0 | T66: 0 | U66: 0 | V66: 0 | W66: 0
A67: Earning Per Share - Diluted | B67: 31.74 | C67: 38.56 | D67: 90.41 | E67: 57.11 | F67: 144.99 | G67: 270.13 | Q67: Proceed from Short Tem Borrowings | R67: 0 | S67: 0 | T67: 0 | U67: 7846.07 | V67: 0 | W67: 8794.21
A68: Dividend Per Share | I68: Employee Stock Options / Others | J68: 2275 | K68: 2275 | L68: 2275 | M68: 2275 | N68: 775 | O68: 0 | Q68: Proceed from Deposits | R68: 0 | S68: 0 | T68: 0 | U68: 0 | V68: 0 | W68: 0
A69: Interim 1 | B69: 0 | C69: 0 | D69: 0 | E69: 0 | F69: 0 | G69: 0 | I69: Share Application Money Pending Allotment | J69: 0.01 | K69: 0.02 | L69: 0 | M69: 0 | N69: 3.78 | O69: 0 | Q69: Share Application Money | R69: 0 | S69: 0 | T69: 0 | U69: 0 | V69: 0 | W69: 0
A70: Interim 2 | B70: 0 | C70: 0 | D70: 0 | E70: 0 | F70: 0 | G70: 0 | Q70: Cash/Capital Investment Subsidy | R70: 0 | S70: 0 | T70: 0 | U70: 0 | V70: 0 | W70: 0
A71: Interim 3 | B71: 0 | C71: 0 | D71: 0 | E71: 0 | F71: 0 | G71: 0 | I71: Total Stockholders’ Equity | J71: 51934.01 | K71: 63789.84 | L71: 72729.71 | M71: 76838.12 | N71: 95185.12 | O71: 125433.76 | Q71: Loans from a Corporate Body | R71: 0 | S71: 0 | T71: 0 | U71: 0 | V71: 0 | W71: 0
A72: Interim 4 | B72: 0 | C72: 0 | D72: 0 | E72: 0 | F72: 0 | G72: 0 | Q72: Share Application Money Refund | R72: 0 | S72: 0 | T72: 0 | U72: 0 | V72: 0 | W72: 0
A73: Special | B73: 0 | C73: 0 | D73: 0 | E73: 0 | F73: 0 | G73: 0 | I73: Total Equity | J73: 51934.01 | K73: 63789.84 | L73: 72729.71 | M73: 76838.12 | N73: 95185.12 | O73: 125433.76 | Q73: On Redemption of Debenture | R73: 0 | S73: 0 | T73: 0 | U73: 0 | V73: 0 | W73: 0
A74: Final | B74: 10 | C74: 10 | D74: 13 | E74: 10 | F74: 25 | G74: 51 | Q74: Of the Long Tem Borrowings | R74: 0 | S74: 0 | T74: -4448.06 | U74: -2866.18 | V74: -20275.68 | W74: -9380.72
A75: Total Dividend Per Share | B75: 10 | C75: 10 | D75: 13 | E75: 10 | F75: 25 | G75: 51 | I75: Non-Current Liabilities: | Q75: Of the short term Borrowings | R75: 0 | S75: 0 | T75: -26.35 | U75: 0 | V75: -8447.6 | W75: 0
A76: Dividend Percentage | I76: Long Term Borrowings | J76: 24694.37 | K76: 24568.95 | L76: 26651.19 | M76: 31381.96 | N76: 31545.41 | O76: 20290.81 | Q76: Of financial Liabilities | R76: -111.63 | S76: -108.14 | T76: -89.25 | U76: -260.66 | V76: -488.39 | W76: -483.03
A77: Interim 1 | B77: 0 | C77: 0 | D77: 0 | E77: 0 | F77: 0 | G77: 0 | I77: Others Financial Liabilities - Long-term | J77: 197.55 | K77: 89.86 | L77: 184.89 | M77: 416.14 | N77: 529.81 | O77: 893.41 | Q77: Dividend Paid | R77: -776.97 | S77: -971.22 | T77: -1145.92 | U77: -1489.67 | V77: -1145.92 | W77: -3007.08
A78: Interim 2 | B78: 0 | C78: 0 | D78: 0 | E78: 0 | F78: 0 | G78: 0 | I78: Non Current Tax Liabilities - Long-term | J78: 0 | K78: 0 | L78: 0 | M78: 0 | N78: 0 | O78: 0 | Q78: Shelter Assistance Reserve | R78: 0 | S78: 0 | T78: 0 | U78: 0 | V78: 0 | W78: 0
A79: Interim 3 | B79: 0 | C79: 0 | D79: 0 | E79: 0 | F79: 0 | G79: 0 | I79: Long-term Provisions | J79: 2024.74 | K79: 1961.21 | L79: 1918.18 | M79: 2113.56 | N79: 2572.23 | O79: 2685 | Q79: Interest Paid | R79: -2624.51 | S79: -2769.66 | T79: -2607.88 | U79: -3084.03 | V79: -4311.1 | W79: -2868.17
A80: Interim 4 | B80: 0 | C80: 0 | D80: 0 | E80: 0 | F80: 0 | G80: 0 | I80: Deferred Tax Liabilities (Net) | J80: 6111.27 | K80: 6259.09 | L80: 7807 | M80: 5862.28 | N80: 8517.78 | O80: 8087.57 | Q80: Others | R80: -3766.61 | S80: -1072.63 | T80: -480.73 | U80: -568.66 | V80: -1734.9 | W80: -785.86
A81: Special | B81: 0 | C81: 0 | D81: 0 | E81: 0 | F81: 0 | G81: 0 | I81: Insurance Related Liabilities | J81: 0 | K81: 0 | L81: 0 | M81: 0 | N81: 0 | O81: 0 | Q81: Net Inc/(Dec) in Cash and Cash Equivalent | R81: -69.47 | S81: 3683.68 | T81: -4044.04 | U81: 448.79 | V81: 504.06 | W81: 450.28
A82: Final | B82: 10 | C82: 10 | D82: 13 | E82: 10 | F82: 25 | G82: 51 | I82: Other Non-Current Liabilities | J82: 3447.14 | K82: 2838.05 | L82: 2613.74 | M82: 2909.2 | N82: 8059.36 | O82: 7203.94 | Q82: Cash and Cash Equivalents at End of the year | R82: 905.21 | S82: 4588.89 | T82: 544.85 | U82: 993.64 | V82: 2221.31 | W82: 2671.59
A83: Total Dividend Percentage | B83: 100 | C83: 100 | D83: 130 | E83: 100 | F83: 250 | G83: 510 | I83: Total Reported Non-current Liabilities | J83: 36475.07 | K83: 35717.16 | L83: 39175 | M83: 42683.14 | N83: 55238.21 | O83: 42887.63 | Q83: Disclaimer:- | W83: Capitaline Database has taken due care and caution in compilation of data.However, Capitaline Database makes no warranty that the service will meet all your requirements, the service will be uninterrupted, timely, complete, error-free, or the results that may be obtained from the use of the service will be accurate. Use of data from Capitaline is permitted only to the licensee and its employees internal usage.The Licensee shall not use Capitaline or data from Capitaline or permit any third party to do so in order to provide data processing ,advisory, research service to third party by way of trade or otherwise. The Licensee shall also not make the data available on a network that extends beyond the Licensee's premises . In the event of unauthorised use of Capitaline or data from Capitaline by the Licensee, Capital Market publishers india pvt ltd will terminate the subscription immediately.
A84: Total Dividend | B84: 971.22 | C84: 1144.75 | D84: 1565.36 | E84: 1204.13 | F84: 3010.32 | G84: 6233.95
A85: Preference Dividend | B85: 0 | C85: 0 | D85: 0 | E85: 0 | F85: 0 | G85: 0 | I85: Current Liabilities:
A86: Weighted Average Number of Shares in Issue - Basic | B86: 103.05 | C86: 103.62 | D86: 114.59 | E86: 114.59 | F86: 116.53 | G86: 122.11
A87: Weighted Average Number of Shares in Issue - Diluted | B87: 103.06 | C87: 103.64 | D87: 114.61 | E87: 114.6 | F87: 116.54 | G87: 122.2 | I87: Short Term Borrowings | J87: 3239.67 | K87: 669.88 | L87: 8.09 | M87: 7857.27 | N87: 984.68 | O87: 11984.66
A88: Interim Dividend Amount | B88: 0 | C88: 0 | D88: 0 | E88: 0 | F88: 0 | G88: 0 | I88: Trade Payables | J88: 10717.44 | K88: 11242.75 | L88: 10969.56 | M88: 10600.96 | N88: 13426.21 | O88: 21091.14
A89: Final Dividend Amount | B89: 971.22 | C89: 1144.75 | D89: 1565.36 | E89: 1204.13 | F89: 3010.32 | G89: 6233.95 | I89: Others Financial Liabilities - Short-term | J89: 4332.52 | K89: 6557.81 | L89: 7011.92 | M89: 5483.24 | N89: 4702.97 | O89: 5219.02
A90: Special Dividend Amount | B90: 0 | C90: 0 | D90: 0 | E90: 0 | F90: 0 | G90: 0 | I90: Current Tax Liabilities - Short-term | J90: 465.72 | K90: 454.06 | L90: 358.14 | M90: 277.26 | N90: 653.75 | O90: 1079.69
A91: Dividend Amount Calculated | B91: 0 | C91: 0 | D91: 0 | E91: 0 | F91: 0 | G91: 0 | I91: Provisions | J91: 700.6 | K91: 735.28 | L91: 778.23 | M91: 663.86 | N91: 1076.91 | O91: 1082.42
A92: Other Dividend Amount | B92: 0 | C92: 0 | D92: 0 | E92: 0 | F92: 0 | G92: 0 | I92: Insurance Related Liabilities | J92: 0 | K92: 0 | L92: 0 | M92: 0 | N92: 0 | O92: 0
A93: Disclaimer:- | I93: Other Current Liabilities | J93: 3600.38 | K93: 5947.56 | L93: 6467.71 | M93: 5988.71 | N93: 8701.3 | O93: 12685.76
I94: Liabilities Directly Associated with Assets Classified as Held for Sale | J94: 0 | K94: 0 | L94: 0 | M94: 0 | N94: 0 | O94: 0
I95: Total Current Liabilities | J95: 23056.33 | K95: 25607.34 | L95: 25593.65 | M95: 30871.3 | N95: 30067.6 | O95: 53664.83
I97: Total Equity and Liabilities | J97: 111465.41 | K97: 125114.34 | L97: 137498.36 | M97: 150392.56 | N97: 180490.93 | O97: 221986.22
I99: Contingent Liabilities and Commitments (to the Extent Not Provided for) | J99: 25991.17 | K99: 28359.62 | L99: 35561.45 | M99: 39253.01 | N99: 40644.99 | O99: 47846.78
I100: Book Value of Share | J100: 472.56 | K100: 535.82 | L100: 614.24 | M100: 652.21 | N100: 785.21 | O100: 1019.17

Sheet Sources
A1: Sr. No. | B1: Detail of Assumption | C1: Assumed Figure | D1: Remarks | E1: URL
A2: 1 | B2: Actual Financial Statement data for last 5 years | C2: 0 | D2: Financial statements has been taken for the last five years from capitaline database | E2: https://awsone.capitaline.com/index.html#/Company/Condensed/condensed?
B3: Revenue Growth | C3: 0.0961 | D3: India's steel consumption is predicted to increase by 230 MT by 2030 from 130 MT in 2022 as per ibef report. Therefore, an average of 9.61% gowth every year. | E3: https://www.ibef.org/industry/steel/showcase/tata-steel
A4: 2 | B4: Tax Rate | C4: 0.246 | D4: As mentioned in Annual Report 2025 | E4: https://www.divislabs.com/wp-content/uploads/2025/08/Annual-Report-2024-25.pdf
A5: 3 | B5: Data period used for Stock and Market Index Price | C5: 0 | D5: 5 years daily price changes of BSE Sensex and Divi Laboratory. has been used to calculate Beta. | E5: https://www.bseindia.com/markets/equity/EQReports/StockPrcHistori
A6: 4 | B6: Risk Free Rate | C6: 0.07129 | D6: Risk free rate is 10 year government yield bond rate as on 07-01-2023 | E6: http://www.worldgovernmentbonds.com/bond-historical-data/india/10-years/
A7: 5 | B7: Market Risk Premium | C7: 0.0708 | D7: Equity Risk premium of India is 6.85% as per knoema | E7: https://knoema.com/NYCCDSRP2019JAN/country-default-spreads-and-risk-premiums?tsId=1004460
A8: 6 | B8: Perpetuity Growth Rate for Terminal Value | C8: 0.0825 | D8: Ideally, it should not exceed the growth rate of economy. And one of the proxy for economy growth rate could be GDP growth. Hence, an approximate 8.25% growth rate has been taken based on the average GDP growth rate of 5 years starting 2020 to 2024. GDP growth for 2020 's -5.8% has been excluded from the average. | E8: https://data.worldbank.org/indicator/NY.GDP.MKTP.KD.ZG?locations=IN
A9: 7 | B9: Basis for selection of peer companies | C9: 0 | D9: Top 4 pharma company in India | E9: Top Companies in India by Market Capitalisation
A10: 8 | B10: Sensitivity Analysis | C10: 0 | D10: In this valuation, two variable sensitivity analysis has been used based on WACC and perpetual growth rate
A11: 9 | B11: Peer Comparison | C11: 0 | D11: For peer comparison, the data and ratios has been taken from money control and smart investing | E11: https://www.moneycontrol.com/india/stockpricequote/steel-large/

Sheet Assumptions
I1: Scenarios: | K1: Y-o-Y Growth
A2: Selected case | B2: Case 1 | I2: Case 1 | J2: Optimistic case | K2: =K3+0.02 -> 0.11251434
I3: Case 2 | J3: Base case | K3: =AVERAGE(C9:F9) -> 0.092514337
I4: Case 3 | J4: Worst case | K4: =K3-0.02 -> 0.072514337
A5: P&L Assumptions
K6: INR in Cr.
A7: Particulars | B7: 2021 Actual | C7: 2022 Actual | D7: 2023 Actual | E7: 2024 Actual | F7: 2025 Actual | G7: 2026 Forecast | H7: 2027 Forecast | I7: 2028 Forecast | J7: 2029 Forecast | K7: 2030 Forecast
A8: Revenue from Operations | B8: ='Financial Statements'!B7 -> 6798.61 | C8: ='Financial Statements'!C7 -> 8879.82 | D8: ='Financial Statements'!D7 -> 7625 | E8: ='Financial Statements'!E7 -> 7665 | F8: ='Financial Statements'!F7 -> 9198 | G8: =F8*(1+G9) -> 10232.907 | H8: =G8*(1+H9) -> 11384.256 | I8: =H8*(1+I9) -> 12665.148 | J8: =I8*(1+J9) -> 14090.158 | K8: =J8*(1+K9) -> 15675.503
A9: y-o-y growth% | C9: =(C8-B8)/B8 -> 0.30612287 | D9: =(D8-C8)/C8 -> -0.14131142 | E9: =(E8-D8)/D8 -> 0.0052459016 | F9: =(F8-E8)/E8 -> 0.2 | G9: =VLOOKUP(B2,I1:K4,3,FALSE) -> 0.11251434 | H9: =VLOOKUP($B$2,$I$2:$K$4,3,0) -> 0.11251434 | I9: =VLOOKUP($B$2,$I$2:$K$4,3,0) -> 0.11251434 | J9: =VLOOKUP($B$2,$I$2:$K$4,3,0) -> 0.11251434 | K9: =VLOOKUP($B$2,$I$2:$K$4,3,0) -> 0.11251434
A11: Other revenues | B11: ='Financial Statements'!B8 -> 62.53 | C11: ='Financial Statements'!C8 -> 111.26 | D11: ='Financial Statements'!D8 -> 349 | E11: ='Financial Statements'!E8 -> 337 | F11: ='Financial Statements'!F8 -> 352 | G11: =G8*G12 -> 306.44028 | H11: =H8*H12 -> 388.16178 | I11: =I8*I12 -> 486.46498 | J11: =J8*J12 -> 520.45642 | K11: =K8*K12 -> 556.9802
A12: % of revenues | B12: =B11/B8 -> 0.0091974683 | C12: =C11/C8 -> 0.012529533 | D12: =D11/D8 -> 0.045770492 | E12: =E11/E8 -> 0.04396608 | F12: =F11/F8 -> 0.038269189 | G12: =AVERAGE(B12:F12) -> 0.029946552 | H12: =AVERAGE(C12:G12) -> 0.034096369 | I12: =AVERAGE(D12:H12) -> 0.038409736 | J12: =AVERAGE(E12:I12) -> 0.036937585 | K12: =AVERAGE(F12:J12) -> 0.035531886
A14: Cost of goods sold | B14: ='Financial Statements'!B10 -> 521.44 | C14: ='Financial Statements'!C10 -> 645.43 | D14: ='Financial Statements'!D10 -> 781 | E14: ='Financial Statements'!E10 -> 776 | F14: ='Financial Statements'!F10 -> 741 | G14: =G8*G15 -> 887.4175 | H14: =H8*H15 -> 1010.0876 | I14: =I8*I15 -> 1164.371 | J14: =J8*J15 -> 1265.815 | K14: =K8*K15 -> 1372.4891
A15: % of revenues | B15: =B14/B8 -> 0.076698031 | C15: =C14/C8 -> 0.072685032 | D15: =D14/D8 -> 0.10242623 | E15: =E14/E8 -> 0.1012394 | F15: =F14/F8 -> 0.080560992 | G15: =AVERAGE(B15:F15) -> 0.086721937 | H15: =AVERAGE(C15:G15) -> 0.088726718 | I15: =AVERAGE(D15:H15) -> 0.091935055 | J15: =AVERAGE(E15:I15) -> 0.08983682 | K15: =AVERAGE(F15:J15) -> 0.087556304
A17: Employee benefit Expenses | B17: ='Financial Statements'!B12 -> 808.68 | C17: ='Financial Statements'!C12 -> 926.55 | D17: ='Financial Statements'!D12 -> 953 | E17: ='Financial Statements'!E12 -> 1067 | F17: ='Financial Statements'!F12 -> 1210 | G17: =G8*G18 -> 1266.8938 | H17: =H8*H18 -> 1420.4985 | I17: =I8*I18 -> 1632.0852 | J17: =J8*J18 -> 1826.6541 | K17: =K8*K18 -> 2002.1955
A18: % of revenues | B18: =B17/B8 -> 0.11894784 | C18: =C17/C8 -> 0.10434333 | D18: =D17/D8 -> 0.12498361 | E18: =E17/E8 -> 0.13920417 | F18: =F17/F8 -> 0.13155034 | G18: =AVERAGE(B18:F18) -> 0.12380586 | H18: =AVERAGE(C18:G18) -> 0.12477746 | I18: =AVERAGE(D18:H18) -> 0.12886429 | J18: =AVERAGE(E18:I18) -> 0.12964042 | K18: =AVERAGE(F18:J18) -> 0.12772767
A20: Finance Cost | B20: ='Financial Statements'!B17 -> 1.81 | C20: ='Financial Statements'!C17 -> 1.73 | D20: ='Financial Statements'!D17 -> 2 | E20: ='Financial Statements'!E17 -> 4 | F20: ='Financial Statements'!F17 -> 2 | G20: =G8*G21 -> 2.9934136 | H20: =H8*H21 -> 3.3900906 | I20: =I8*I21 -> 4.0323349 | J20: =J8*J21 -> 4.6440806 | K20: =K8*K21 -> 4.5638671
A21: % of revenues | B21: =B20/B8 -> 0.00026623089 | C21: =C20/C8 -> 0.00019482377 | D21: =D20/D8 -> 0.00026229508 | E21: =E20/E8 -> 0.00052185258 | F21: =F20/F8 -> 0.00021743857 | G21: =AVERAGE(B21:F21) -> 0.00029252818 | H21: =AVERAGE(C21:G21) -> 0.00029778764 | I21: =AVERAGE(D21:H21) -> 0.00031838041 | J21: =AVERAGE(E21:I21) -> 0.00032959747 | K21: =AVERAGE(F21:J21) -> 0.00029114645
A23: Other Expenses | B23: ='Financial Statements'!B13 -> 292.53 | C23: ='Financial Statements'!C13 -> 340.16 | D23: ='Financial Statements'!D13 -> 402 | E23: ='Financial Statements'!E13 -> 367 | F23: ='Financial Statements'!F13 -> 449 | G23: =G8*G24 -> 472.25119 | H23: =H8*H24 -> 532.49531 | I23: =I8*I24 -> 613.85743 | J23: =J8*J24 -> 670.93991 | K23: =K8*K24 -> 745.60779
A24: % of revenues | B24: =B23/B8 -> 0.043027913 | C24: =C23/C8 -> 0.038307083 | D24: =D23/D8 -> 0.052721311 | E24: =E23/E8 -> 0.047879974 | F24: =F23/F8 -> 0.04881496 | G24: =AVERAGE(B24:F24) -> 0.046150248 | H24: =AVERAGE(C24:G24) -> 0.046774715 | I24: =AVERAGE(D24:H24) -> 0.048468242 | J24: =AVERAGE(E24:I24) -> 0.047617628 | K24: =AVERAGE(F24:J24) -> 0.047565159
A26: Taxes | B26: ='Financial Statements'!B20 -> 609.05 | C26: ='Financial Statements'!C20 -> 637.2 | D26: ='Financial Statements'!D20 -> 438 | E26: ='Financial Statements'!E20 -> 511 | F26: ='Financial Statements'!F20 -> 793 | G26: =G27*'Financial Statements'!G18 -> 1878.3113 | H26: =H27*'Financial Statements'!H18 -> 2092.0845 | I26: =I27*'Financial Statements'!I18 -> 2313.4616 | J26: =J27*'Financial Statements'!J18 -> 2578.8725 | K26: =K27*'Financial Statements'!K18 -> 2881.5532
A27: % of EBT | B27: =B26/'Financial Statements'!B18 -> 0.12224936 | C27: =C26/'Financial Statements'!C18 -> 0.09416758 | D27: =D26/'Financial Statements'!D18 -> 0.079723335 | E27: =E26/'Financial Statements'!E18 -> 0.094419808 | F27: =F26/'Financial Statements'!F18 -> 0.11753372 | G27: 0.25168 | H27: 0.25168 | I27: 0.25168 | J27: 0.25168 | K27: 0.25168
A29: Dividend | B29: ='Financial Statements'!B24 -> 0 | C29: ='Financial Statements'!C24 -> 0 | D29: ='Financial Statements'!D24 -> 0 | E29: ='Financial Statements'!E24 -> 0 | F29: ='Financial Statements'!F24 -> 0 | G29: =G30*'Financial Statements'!G22 -> 0 | H29: =H30*'Financial Statements'!H22 -> 0 | I29: =I30*'Financial Statements'!I22 -> 0 | J29: =J30*'Financial Statements'!J22 -> 0 | K29: =K30*'Financial Statements'!K22 -> 0
A30: Dividend Payout Ratio | B30: =B29/'Financial Statements'!B22 -> 0 | C30: =C29/'Financial Statements'!C22 -> 0 | D30: =D29/'Financial Statements'!D22 -> 0 | E30: =E29/'Financial Statements'!E22 -> 0 | F30: =F29/'Financial Statements'!F22 -> 0 | G30: =AVERAGE(B30:F30) -> 0 | H30: =AVERAGE(C30:G30) -> 0 | I30: =AVERAGE(D30:H30) -> 0 | J30: =AVERAGE(E30:I30) -> 0 | K30: =AVERAGE(F30:J30) -> 0
A32: BS Assumptions
A33: Particulars | B33: 2018 Actual | C33: 2019 Actual | D33: 2020 Actual | E33: 2021 Actual | F33: 2022 Actual | G33: 2023 Forecast | H33: 2024 Forecast | I33: 2025 Forecast | J33: 2026 Forecast | K33: 2027 Forecast
A34: Trade receivable | B34: ='Financial Statements'!B56 -> 1745.56 | C34: ='Financial Statements'!C56 -> 2569.9 | D34: ='Financial Statements'!D56 -> 1964 | E34: ='Financial Statements'!E56 -> 2273 | F34: ='Financial Statements'!F56 -> 2855 | G34: =(G35/365*G8) -> 2887.0541 | H34: =(H35/365*H8) -> 3269.6798 | I34: =(I35/365*I8) -> 3631.9972 | J34: =(J35/365*J8) -> 4122.9277 | K34: =(K35/365*K8) -> 4574.4881
A35: Days receivables | B35: =B34*365/B8 -> 93.714656 | C35: =C34*365/C8 -> 105.63429 | D35: =D34*365/D8 -> 94.014426 | E35: =E34*365/E8 -> 108.2381 | F35: =F34*365/F8 -> 113.29365 | G35: =(AVERAGE(B35:F35)) -> 102.97902 | H35: =(AVERAGE(C35:G35)) -> 104.8319 | I35: =(AVERAGE(D35:H35)) -> 104.67142 | J35: =(AVERAGE(E35:I35)) -> 106.80282 | K35: =(AVERAGE(F35:J35)) -> 106.51576
A37: Inventory | B37: ='Financial Statements'!B55 -> 2042.7 | C37: ='Financial Statements'!C55 -> 2644.05 | D37: ='Financial Statements'!D55 -> 2781 | E37: ='Financial Statements'!E55 -> 2985 | F37: ='Financial Statements'!F55 -> 3033 | G37: =(G38/365*G14) -> 3463.5157 | H37: =(H38/365*H14) -> 3939.3566 | I37: =(I38/365*I14) -> 4495.2912 | J37: =(J38/365*J14) -> 4962.8558 | K37: =(K38/365*K14) -> 5401.4121
A38: Days Inventory | B38: =B37*365/B14 -> 1429.8587 | C38: =C37*365/C14 -> 1495.2485 | D38: =D37*365/D14 -> 1299.6991 | E38: =E37*365/E14 -> 1404.0271 | F38: =F37*365/F14 -> 1493.9879 | G38: =(AVERAGE(B38:F38)) -> 1424.5642 | H38: =(AVERAGE(C38:G38)) -> 1423.5054 | I38: =(AVERAGE(D38:H38)) -> 1409.1567 | J38: =(AVERAGE(E38:I38)) -> 1431.0482 | K38: =(AVERAGE(F38:J38)) -> 1436.4525
A41: Other current liabilities | B41: ='Financial Statements'!B43 -> 1086.03 | C41: ='Financial Statements'!C43 -> 1164.25 | D41: ='Financial Statements'!D43 -> 1074 | E41: ='Financial Statements'!E43 -> 1210 | F41: ='Financial Statements'!F43 -> 1364 | G41: =(G8*G42) -> 1510.0922 | H41: =(H8*H42) -> 1652.2881 | I41: =(I8*I42) -> 1873.7228 | J41: =(J8*J42) -> 2104.5255 | K41: =(K8*K42) -> 2314.6695
A42: as a % of revenue | B42: =B41/B8 -> 0.15974295 | C42: =C41/C8 -> 0.13111189 | D42: =D41/D8 -> 0.14085246 | E42: =E41/E8 -> 0.1578604 | F42: =F41/F8 -> 0.14829311 | G42: =(AVERAGE(B42:F42)) -> 0.14757216 | H42: =(AVERAGE(C42:G42)) -> 0.145138 | I42: =(AVERAGE(D42:H42)) -> 0.14794323 | J42: =(AVERAGE(E42:I42)) -> 0.14936138 | K42: =(AVERAGE(F42:J42)) -> 0.14766158
A44: Other current assets | B44: ='Financial Statements'!B59 -> 151.3 | C44: ='Financial Statements'!C59 -> 215.81 | D44: ='Financial Statements'!D59 -> 199.2 | E44: ='Financial Statements'!E59 -> 318 | F44: ='Financial Statements'!F59 -> 367 | G44: =(G8*G45) -> 315.31642 | H44: =(H8*H45) -> 370.28255 | I44: =(I8*I45) -> 432.77229 | J44: =(J8*J45) -> 504.13854 | K44: =(K8*K45) -> 542.96682
A45: as a % of revenue | B45: =B44/B8 -> 0.022254549 | C45: =C44/C8 -> 0.024303421 | D45: =D44/D8 -> 0.02612459 | E45: =E44/E8 -> 0.04148728 | F45: =F44/F8 -> 0.039899978 | G45: =(AVERAGE(B45:F45)) -> 0.030813964 | H45: =(AVERAGE(C45:G45)) -> 0.032525846 | I45: =(AVERAGE(D45:H45)) -> 0.034170332 | J45: =(AVERAGE(E45:I45)) -> 0.03577948 | K45: =(AVERAGE(F45:J45)) -> 0.03463792

Sheet Financial Statements
A1: FINANCIAL STATEMENTS OF Divi Laboratory | B1: ACTUAL PERIOD | G1: FORECASTED PERIOD
A2: Number of Days | B2: 365 | C2: 365 | D2: 365 | E2: 365 | F2: 365 | G2: 365 | H2: 365 | I2: 365 | J2: 365 | K2: 365
A4: Profit and Loss Statement
K5: INR in Cr.
A6: Particulars | B6: 2021 Actual | C6: 2022 Actual | D6: 2023 Actual | E6: 2024 Actual | F6: 2025 Actual | G6: 2026 Forecast | H6: 2027 Forecast | I6: 2028 Forecast | J6: 2029 Forecast | K6: 2030 Forecast | L6: Trend
A7: Sales Turnover | B7: 6798.61 | C7: 8879.82 | D7: 7625 | E7: 7665 | F7: 9198 | G7: =Assumptions!G8 -> 10232.907 | H7: =Assumptions!H8 -> 11384.256 | I7: =Assumptions!I8 -> 12665.148 | J7: =Assumptions!J8 -> 14090.158 | K7: =Assumptions!K8 -> 15675.503
A8: Other Income | B8: 62.53 | C8: 111.26 | D8: 349 | E8: 337 | F8: 352 | G8: =Assumptions!G11 -> 306.44028 | H8: =Assumptions!H11 -> 388.16178 | I8: =Assumptions!I11 -> 486.46498 | J8: =Assumptions!J11 -> 520.45642 | K8: =Assumptions!K11 -> 556.9802
A9: Total Income | B9: =SUM(B7:B8) -> 6861.14 | C9: =SUM(C7:C8) -> 8991.08 | D9: =SUM(D7:D8) -> 7974 | E9: =SUM(E7:E8) -> 8002 | F9: =SUM(F7:F8) -> 9550 | G9: =SUM(G7:G8) -> 10539.347 | H9: =SUM(H7:H8) -> 11772.417 | I9: =SUM(I7:I8) -> 13151.613 | ... K9: =SUM(K7:K8) -> 16232.483
A10: Cost of Goods sold | B10: 521.44 | C10: 645.43 | D10: 781 | E10: 776 | F10: 741 | G10: =Assumptions!G14 -> 887.4175 | H10: =Assumptions!H14 -> 1010.0876 | I10: =Assumptions!I14 -> 1164.371 | J10: =Assumptions!J14 -> 1265.815 | K10: =Assumptions!K14 -> 1372.4891
A11: Gross Margin | B11: =B9-B10 -> 6339.7 | C11: =C9-C10 -> 8345.65 | D11: =D9-D10 -> 7193 | E11: =E9-E10 -> 7226 | F11: =F9-F10 -> 8809 | G11: =G9-G10 -> 9651.9297 | H11: =H9-H10 -> 10762.33 | I11: =I9-I10 -> 11987.242 | ... K11: =K9-K10 -> 14859.994
A12: Employee Cost | B12: 808.68 | C12: 926.55 | D12: 953 | E12: 1067 | F12: 1210 | G12: =Assumptions!G17 -> 1266.8938 | H12: =Assumptions!H17 -> 1420.4985 | I12: =Assumptions!I17 -> 1632.0852 | J12: =Assumptions!J17 -> 1826.6541 | K12: =Assumptions!K17 -> 2002.1955
A13: Selling and Administration Expenses | B13: 292.53 | C13: 340.16 | D13: 402 | E13: 367 | F13: 449 | G13: =Assumptions!G23 -> 472.25119 | H13: =Assumptions!H23 -> 532.49531 | I13: =Assumptions!I23 -> 613.85743 | J13: =Assumptions!J23 -> 670.93991 | K13: =Assumptions!K23 -> 745.60779
A14: EBITDA | B14: =B11-B12-B13 -> 5238.49 | C14: =C11-C12-C13 -> 7078.94 | D14: =D11-D12-D13 -> 5838 | E14: =E11-E12-E13 -> 5792 | F14: =F11-F12-F13 -> 7150 | G14: =G11-G12-G13 -> 7912.7846 | H14: =H11-H12-H13 -> 8809.3359 | I14: =I11-I12-I13 -> 9741.2989 | ... K14: =K11-K12-K13 -> 12112.191
A15: Depreciation | B15: 254.65 | C15: 310.55 | D15: 342 | E15: 376 | F15: 401 | G15: ='PPE '!G8 -> 446.698 | H15: ='PPE '!H8 -> 493.46753 | I15: ='PPE '!I8 -> 545.19101 | J15: ='PPE '!J8 -> 595.92882 | K15: ='PPE '!K8 -> 658.35324
A16: EBIT | B16: =B14-B15 -> 4983.84 | C16: =C14-C15 -> 6768.39 | D16: =D14-D15 -> 5496 | E16: =E14-E15 -> 5416 | F16: =F14-F15 -> 6749 | G16: =G14-G15 -> 7466.0866 | H16: =H14-H15 -> 8315.8684 | I16: =I14-I15 -> 9196.1079 | ... K16: =K14-K15 -> 11453.838
A17: Interest | B17: 1.81 | C17: 1.73 | D17: 2 | E17: 4 | F17: 2 | G17: =Assumptions!G20 -> 2.9934136 | H17: =Assumptions!H20 -> 3.3900906 | I17: =Assumptions!I20 -> 4.0323349 | J17: =Assumptions!J20 -> 4.6440806 | K17: =Assumptions!K20 -> 4.5638671
A18: EBT | B18: =B16-B17 -> 4982.03 | C18: =C16-C17 -> 6766.66 | D18: =D16-D17 -> 5494 | E18: =E16-E17 -> 5412 | F18: =F16-F17 -> 6747 | G18: =G16-G17 -> 7463.0932 | H18: =H16-H17 -> 8312.4783 | I18: =I16-I17 -> 9192.0755 | ... K18: =K16-K17 -> 11449.274
A19: Tax Rate | B19: 0.2562 | C19: 0.198 | D19: 0.2319 | E19: 0.2608 | F19: 0.2458 | G19: =Assumptions!G27 -> 0.25168 | H19: =Assumptions!H27 -> 0.25168 | I19: =Assumptions!I27 -> 0.25168 | J19: =Assumptions!J27 -> 0.25168 | K19: =Assumptions!K27 -> 0.25168
A20: Current Tax | B20: 609.05 | C20: 637.2 | D20: 438 | E20: 511 | F20: 793 | G20: =Assumptions!G26 -> 1878.3113 | H20: =Assumptions!H26 -> 2092.0845 | I20: =Assumptions!I26 -> 2313.4616 | J20: =Assumptions!J26 -> 2578.8725 | K20: =Assumptions!K26 -> 2881.5532
A21: Deferred Tax | B21: 64.1 | C21: 90.78 | D21: 108 | E21: 45 | F21: -73 | G21: 0 | H21: 0 | I21: 0 | J21: 0 | K21: 0
A22: Net Income | B22: =B18-B20-B21 -> 4308.88 | C22: =C18-C20-C21 -> 6038.68 | D22: =D18-D20-D21 -> 4948 | E22: =E18-E20-E21 -> 4856 | F22: =F18-F20-F21 -> 6027 | G22: =G18-G20-G21 -> 5584.7819 | H22: =H18-H20-H21 -> 6220.3938 | I22: =I18-I20-I21 -> 6878.614 | ... K22: =K18-K20-K21 -> 8567.7205
A23: EPS | B23: =B22/B31 -> 81.161801 | C23: =C22/C31 -> 113.74421 | D23: =D22/D31 -> 93.358491 | E23: =E22/E31 -> 91.622642 | F23: =F22/F31 -> 113.71698 | G23: =G22/G31 -> 105.37324 | H23: =H22/H31 -> 117.36592 | I23: =I22/I31 -> 129.78517 | ... K23: =K22/K31 -> 161.6551
A24: Dividend | B24: 0 | C24: 0 | D24: 0 | E24: 0 | F24: 0 | G24: =Assumptions!G29 -> 0 | H24: =Assumptions!H29 -> 0 | I24: =Assumptions!I29 -> 0 | J24: =Assumptions!J29 -> 0 | K24: =Assumptions!K29 -> 0
A25: Rate of Dividend | B25: =B24/B31 -> 0 | C25: =C24/C31 -> 0 | D25: =D24/D31 -> 0 | E25: =E24/E31 -> 0 | F25: =F24/F31 -> 0 | G25: =G24/G31 -> 0 | H25: =H24/H31 -> 0 | I25: =I24/I31 -> 0 | ... K25: =K24/K31 -> 0
A28: Balance Sheet
A30: INR in Cr. | B30: 2021 Actual | C30: 2022 Actual | D30: 2023 Actual | E30: 2024 Actual | F30: 2025 Actual | G30: 2026 Forecast | H30: 2027 Forecast | I30: 2028 Forecast | J30: 2029 Forecast | K30: 2030 Forecast | L30: Trend
A31: Share Capital | B31: 53.09 | C31: 53.09 | D31: 53 | E31: 53 | F31: 53 | G31: =F31 -> 53 | H31: =G31 -> 53 | I31: =H31 -> 53 | J31: =I31 -> 53 | K31: =J31 -> 53 | L31: Constant
A32: Reserves | B32: 9218.48 | C32: 11638.26 | D32: 12652 | E32: 13431 | F32: 14842 | G32: =F32+G22-F24 -> 20426.782 | H32: =G32+H22-G24 -> 26647.176 | I32: =H32+I22-H24 -> 33525.79 | J32: =I32+J22-I24 -> 41193.55 | K32: =J32+K22-J24 -> 49761.27 | L32: Opening + Net Income-Dividend
A33: Total Equity | B33: =SUM(B31:B32) -> 9271.57 | C33: =SUM(C31:C32) -> 11691.35 | D33: =SUM(D31:D32) -> 12705 | E33: =SUM(E31:E32) -> 13484 | F33: =SUM(F31:F32) -> 14895 | G33: =SUM(G31:G32) -> 20479.782 | H33: =SUM(H31:H32) -> 26700.176 | I33: =SUM(I31:I32) -> 33578.79 | ... K33: =SUM(K31:K32) -> 49814.27
A35: Secured Loans | B35: 0.35 | C35: 0 | D35: 0 | E35: 0 | F35: 2 | G35: =F35 -> 2 | H35: =G35 -> 2 | I35: =H35 -> 2 | J35: =I35 -> 2 | K35: =J35 -> 2 | L35: Constant
A36: Net Deferred Tax | B36: 338.06 | C36: 421.4 | D36: 537 | E36: 582 | F36: 509 | G36: =F36 -> 509 | H36: =G36 -> 509 | I36: =H36 -> 509 | J36: =I36 -> 509 | K36: =J36 -> 509 | L36: Constant
A37: Other Non-current Liabilities | B37: 0 | C37: 0 | D37: 0 | E37: 0 | F37: 0 | G37: =F37 -> 0 | H37: =G37 -> 0 | I37: =H37 -> 0 | J37: =I37 -> 0 | K37: =J37 -> 0 | L37: Constant
A38: Other Liabilities | B38: 25.25 | C38: 26.71 | D38: 31 | E38: 37 | F38: 0 | G38: =F38 -> 0 | H38: =G38 -> 0 | I38: =H38 -> 0 | J38: =I38 -> 0 | K38: =J38 -> 0 | L38: Constant
A39: Total Liabilities | B39: =SUM(B33:B35,B37:B38) -> 9297.17 | C39: =SUM(C33:C35,C37:C38) -> 11718.06 | D39: =SUM(D33:D35,D37:D38) -> 12736 | E39: =SUM(E33:E35,E37:E38) -> 13521 | F39: =SUM(F33:F35,F37:F38) -> 14897 | G39: =SUM(G33:G35,G37:G38) -> 20481.782 | H39: =SUM(H33:H35,H37:H38) -> 26702.176 | I39: =SUM(I33:I35,I37:I38) -> 33580.79 | ... K39: =SUM(K33:K35,K37:K38) -> 49816.27
A40: Total Non-Current Liabilities | B40: =B35+B36+B37+B38 -> 363.66 | C40: =C35+C36+C37+C38 -> 448.11 | D40: =D35+D36+D37+D38 -> 568 | E40: =E35+E36+E37+E38 -> 619 | F40: =F35+F36+F37+F38 -> 511 | G40: =SUM(G35:G38) -> 511 | H40: =SUM(H35:H38) -> 511 | I40: =SUM(I35:I38) -> 511 | J40: =SUM(J35:J38) -> 511 | K40: =SUM(K35:K38) -> 511
A42: Total Debt | B42: 0.35 | C42: 0 | D42: 0 | E42: 0 | F42: 2 | G42: =F42 -> 2 | H42: =G42 -> 2 | I42: =H42 -> 2 | J42: =I42 -> 2 | K42: =J42 -> 2 | L42: Constant
A43: Current Liabilities | B43: 1086.03 | C43: 1164.25 | D43: 1074 | E43: 1210 | F43: 1364 | G43: =Assumptions!G41 -> 1510.0922 | H43: =Assumptions!H41 -> 1652.2881 | I43: =Assumptions!I41 -> 1873.7228 | J43: =Assumptions!J41 -> 2104.5255 | K43: =Assumptions!K41 -> 2314.6695 | L43: Assumptions
A44: Provisions | B44: 2.51 | C44: 4.15 | D44: 5 | E44: 49 | F44: 54 | G44: =F44 -> 54 | H44: =G44 -> 54 | I44: =H44 -> 54 | J44: =I44 -> 54 | K44: =J44 -> 54 | L44: Constant
A45: Total Current Liabilities | B45: =B43+B44 -> 1088.54 | C45: =C43+C44 -> 1168.4 | D45: =D43+D44 -> 1079 | E45: =E43+E44 -> 1259 | F45: =F43+F44 -> 1418 | G45: =G43+G44 -> 1564.0922 | H45: =H43+H44 -> 1706.2881 | I45: =I43+I44 -> 1927.7228 | ... K45: =K43+K44 -> 2368.6695
A47: Total Liabilities & Equity | B47: =SUM(B39) -> 9297.17 | C47: =SUM(C39) -> 11718.06 | D47: =SUM(D39) -> 12736 | E47: =SUM(E39) -> 13521 | F47: =SUM(F39) -> 14897 | G47: =SUM(G39) -> 20481.782 | H47: =SUM(H39) -> 26702.176 | I47: =SUM(I39) -> 33580.79 | ... K47: =SUM(K39) -> 49816.27
A49: Net Block | B49: 3699.01 | C49: 4320.97 | D49: 4719 | E49: 4737 | F49: 5440 | G49: ='PPE '!G10 -> 6034.5648 | H49: ='PPE '!H10 -> 6624.5312 | I49: ='PPE '!I10 -> 7258.9725 | J49: ='PPE '!J10 -> 7964.4516 | K49: ='PPE '!K10 -> 8881.2952 | L49: Assumptions
A50: Capital Work-In-Progress | B50: 710.62 | C50: 469.93 | D50: 212 | E50: 778 | F50: 1022 | G50: =F50 -> 1022 | H50: =G50 -> 1022 | I50: =H50 -> 1022 | J50: =I50 -> 1022 | K50: =J50 -> 1022 | L50: Constant
A51: Investments | B51: 7.37 | C51: 79.37 | D51: 84 | E51: 89 | F51: 72 | G51: =F51 -> 72 | H51: =G51 -> 72 | I51: =H51 -> 72 | J51: =I51 -> 72 | K51: =J51 -> 72 | L51: Constant
A52: Net Deferred tax | B52: -338.06 | C52: -421.4 | D52: -537 | E52: -582 | F52: -509 | G52: =F52 -> -509 | H52: =G52 -> -509 | I52: =H52 -> -509 | J52: =I52 -> -509 | K52: =J52 -> -509 | L52: Constant
A53: Other Assets | B53: 181.46 | C53: 141.63 | D53: 101 | E53: 186 | F53: 311 | G53: =F53 -> 311 | H53: =G53 -> 311 | I53: =H53 -> 311 | J53: =I53 -> 311 | K53: =J53 -> 311 | L53: Constant
A54: Net Current Assets | B54: =B60-B45 -> 5036.77 | C54: =C60-C45 -> 7127.56 | D54: =D60-D45 -> 8157 | E54: =E60-E45 -> 8313 | F54: =F60-F45 -> 8561 | G54: =G60-G45 -> 13551.218 | H54: =H60-H45 -> 19181.578 | I54: =I60-I45 -> 25425.616 | ... K54: =K60-K45 -> 40038.191
A55: Inventories | B55: 2042.7 | C55: 2644.05 | D55: 2781 | E55: 2985 | F55: 3033 | G55: =Assumptions!G37 -> 3463.5157 | H55: =Assumptions!H37 -> 3939.3566 | I55: =Assumptions!I37 -> 4495.2912 | J55: =Assumptions!J37 -> 4962.8558 | K55: =Assumptions!K37 -> 5401.4121 | L55: Assumptions
A56: Sundry Debtors | B56: 1745.56 | C56: 2569.9 | D56: 1964 | E56: 2273 | F56: 2855 | G56: =Assumptions!G34 -> 2887.0541 | H56: =Assumptions!H34 -> 3269.6798 | I56: =Assumptions!I34 -> 3631.9972 | J56: =Assumptions!J34 -> 4122.9277 | K56: =Assumptions!K34 -> 4574.4881 | L56: Assumptions
A57: Cash and Bank | B57: 2142.01 | C57: 2803.68 | D57: 4188 | E57: 3961 | F57: 3696 | G57: 8369.74 | H57: 13283.83 | I57: 18831.05 | J57: 25065.4 | K57: 32035.96 | L57: Cash Flow Statement
A58: Loans and Advances | B58: 195.04 | C58: 278.33 | D58: 303 | E58: 353 | F58: 395 | G58: =F58 -> 395 | H58: =G58 -> 395 | I58: =H58 -> 395 | J58: =I58 -> 395 | K58: =J58 -> 395 | L58: Constant
A59: Other Current Assets | B59: 151.3 | C59: 215.81 | D59: 199.2 | E59: 318 | F59: 367 | G59: =Assumptions!G44 -> 315.31642 | H59: =Assumptions!H44 -> 370.28255 | I59: =Assumptions!I44 -> 432.77229 | J59: =Assumptions!J44 -> 504.13854 | K59: =Assumptions!K44 -> 542.96682 | L59: Assumptions
A60: Total Current Assets | B60: =SUM(B55,B56,B57,B58,B59)-B59 -> 6125.31 | C60: =SUM(C55,C56,C57,C58,C59)-C59 -> 8295.96 | D60: =SUM(D55,D56,D57,D58,D59)-D59 -> 9236 | E60: =SUM(E55,E56,E57,E58,E59)-E59 -> 9572 | F60: =SUM(F55,F56,F57,F58,F59)-F59 -> 9979 | G60: =SUM(G55,G56,G57,G58,G59)-G59 -> 15115.31 | H60: =SUM(H55,H56,H57,H58,H59)-H59 -> 20887.866 | I60: =SUM(I55,I56,I57,I58,I59)-I59 -> 27353.338 | ... K60: =SUM(K55,K56,K57,K58,K59)-K59 -> 42406.86
A61: Total Assets | B61: =B49+B50+B51+B54+B52+B53 -> 9297.17 | C61: =C49+C50+C51+C54+C52+C53 -> 11718.06 | D61: =D49+D50+D51+D54+D52+D53 -> 12736 | E61: =E49+E50+E51+E54+E52+E53 -> 13521 | F61: =F49+F50+F51+F54+F52+F53 -> 14897 | G61: =G49+G50+G51+G54+G52+G53 -> 20481.782 | H61: =H49+H50+H51+H54+H52+H53 -> 26702.109 | I61: =I49+I50+I51+I54+I52+I53 -> 33580.588 | ... K61: =K49+K50+K51+K54+K52+K53 -> 49815.486
A63: CHECK | B63: =B61-B47 -> 0 | C63: =C61-C47 -> 0 | D63: =D61-D47 -> 0 | E63: =E61-E47 -> 0 | F63: =F61-F47 -> 0 | G63: =G61-G47 -> 0.00054026443 | H63: =H61-H47 -> -0.06621103 | I63: =I61-I47 -> -0.20162939 | ... K63: =K61-K47 -> -0.7844993
A64: Cash Flow Statement
A66: INR in Cr. | B66: 2021 Actual | C66: 2022 Actual | D66: 2023 Actual | E66: 2024 Actual | F66: 2025 Actual | G66: 2026 Forecast | H66: 2027 Forecast | I66: 2028 Forecast | J66: 2029 Forecast | K66: 2030 Forecast | L66: Trend
A67: Profit before tax | G67: =G18 -> 7463.0932 | H67: =H18 -> 8312.4783 | I67: =I18 -> 9192.0755 | J67: =J18 -> 10246.633 | K67: =K18 -> 11449.274
A68: Add: Depreciation | G68: =G15 -> 446.698 | H68: =H15 -> 493.46753 | I68: =I15 -> 545.19101 | J68: =J15 -> 595.92882 | K68: =K15 -> 658.35324
A69: Add: Finance Cost | G69: =G17 -> 2.9934136 | H69: =H17 -> 3.3900906 | I69: =I17 -> 4.0323349 | J69: =J17 -> 4.6440806 | K69: =K17 -> 4.5638671
A70: Cash Flow before Working Capital Changes | G70: =SUM(G67:G69) -> 7912.7846 | H70: =SUM(H67:H69) -> 8809.3359 | I70: =SUM(I67:I69) -> 9741.2989 | J70: =SUM(J67:J69) -> 10847.206 | K70: =SUM(K67:K69) -> 12112.191
A71: Changes in working capital
A72: Inventories | G72: =F55-G55 -> -430.51572 | H72: =G55-H55 -> -475.84087 | I72: =H55-I55 -> -555.93458 | J72: =I55-J55 -> -467.5646 | K72: =J55-K55 -> -438.55628
A73: Trade Receivable | G73: =F56-G56 -> -32.054148 | H73: =G56-H56 -> -382.62563 | I73: =H56-I56 -> -362.31739 | J73: =I56-J56 -> -490.9305 | K73: =J56-K56 -> -451.56042
A74: Other current assets | G74: =-(F59-G59) -> -51.68358 | H74: =-(G59-H59) -> 54.96613 | I74: =-(H59-I59) -> 62.489743 | J74: =-(I59-J59) -> 71.366242 | K74: =-(J59-K59) -> 38.828286
A75: Other current liabilities | G75: =G43-F43 -> 146.09219 | H75: =H43-G43 -> 142.19596 | I75: =I43-H43 -> 221.43466 | J75: =J43-I43 -> 230.80269 | K75: =K43-J43 -> 210.144
A76: Net Changes in working capital | G76: =SUM(G72:G75) -> -368.16126 | H76: =SUM(H72:H75) -> -661.30442 | I76: =SUM(I72:I75) -> -634.32756 | J76: =SUM(J72:J75) -> -656.32616 | K76: =SUM(K72:K75) -> -641.14442
A77: Tax paid | G77: =-G20 -> -1878.3113 | H77: =-H20 -> -2092.0845 | I77: =-I20 -> -2313.4616 | J77: =-J20 -> -2578.8725 | K77: =-K20 -> -2881.5532
A78: Net cash flow from opreating | G78: =G70+G76+G77 -> 5666.3121 | H78: =H70+H76+H77 -> 6055.947 | I78: =I70+I76+I77 -> 6793.5097 | J78: =J70+J76+J77 -> 7612.007 | K78: =K70+K76+K77 -> 8589.4932
A80: Capex | G80: =-'PPE '!G6 -> -1041.2628 | H80: =-'PPE '!H6 -> -1083.434 | I80: =-'PPE '!I6 -> -1179.6322 | J80: =-'PPE '!J6 -> -1301.408 | K80: =-'PPE '!K6 -> -1575.1968
A81: Net cash flow from investing acticituies | G81: =G80 -> -1041.2628 | H81: =H80 -> -1083.434 | I81: =I80 -> -1179.6322 | J81: =J80 -> -1301.408 | K81: =K80 -> -1575.1968
A83: Finace cost | G83: =-G17 -> -2.9934136 | H83: =-H17 -> -3.3900906 | I83: =-I17 -> -4.0323349 | J83: =-J17 -> -4.6440806 | K83: =-K17 -> -4.5638671
A84: Dividend Paid | G84: =-F24 -> 0 | H84: =-G24 -> 0 | I84: =-H24 -> 0 | J84: =-I24 -> 0 | K84: =-J24 -> 0
A85: Net cash flow from financing activities | G85: =SUM(G83:G84) -> -2.9934136 | H85: =SUM(H83:H84) -> -3.3900906 | I85: =SUM(I83:I84) -> -4.0323349 | J85: =SUM(J83:J84) -> -4.6440806 | K85: =SUM(K83:K84) -> -4.5638671
A87: Net changes in cash | G87: =G78+G81+G85 -> 4622.0559 | H87: =H78+H81+H85 -> 4969.1229 | I87: =I78+I81+I85 -> 5609.8452 | J87: =J78+J81+J85 -> 6305.9549 | K87: =K78+K81+K85 -> 7009.7325
A88: Add opening cash | G88: =F57 -> 3696 | H88: =G89 -> 8369.74 | I88: =H89 -> 13283.83 | J88: =I89 -> 18831.05 | K88: =J89 -> 25065.4
A89: Cash at the end | G89: =G57 -> 8369.74 | H89: =H57 -> 13283.83 | I89: =I57 -> 18831.05 | J89: =J57 -> 25065.4 | K89: =K57 -> 32035.96
G90: =G89-G57 -> 0 | H90: =H89-H57 -> 0 | I90: =I89-I57 -> 0 | J90: =J89-J57 -> 0 | K90: =K89-K57 -> 0

Sheet PPE 
A1: PPE SCHEDULE | B1: ACTUAL PERIOD | G1: ='[1]Financial Statements'!G1:K1 -> FORECASTED PERIOD
A3: Particulars | B3: 2021 Actual | C3: 2022 Actual | D3: 2023 Actual | E3: 2024 Actual | F3: 2025 Actual | G3: 2026 Forecast | H3: 2027 Forecast | I3: 2028 Forecast | J3: 2029 Forecast | K3: 2030 Forecast
A4: Revenues | B4: ='Financial Statements'!B9 -> 6861.14 | C4: ='Financial Statements'!C9 -> 8991.08 | D4: ='Financial Statements'!D9 -> 7974 | E4: ='Financial Statements'!E9 -> 8002 | F4: ='Financial Statements'!F9 -> 9550 | G4: ='Financial Statements'!G9 -> 10539.347 | H4: ='Financial Statements'!H9 -> 11772.417 | I4: ='Financial Statements'!I9 -> 13151.613 | ... K4: ='Financial Statements'!K9 -> 16232.483
A5: Opening PP&E | B5: =B10-B6+B8 -> 3043.68 | C5: =B10 -> 3699.01 | D5: =C10 -> 4320.97 | E5: =D10 -> 4719 | F5: =E10 -> 4737 | G5: =F10 -> 5440 | H5: =G10 -> 6034.5648 | I5: =H10 -> 6624.5312 | J5: =I10 -> 7258.9725 | K5: =J10 -> 7964.4516
A6: Capex | B6: 909.98 | C6: =C10-C5+C8 -> 932.51 | D6: =D10-D5+D8 -> 740.03 | E6: =E10-E5+E8 -> 394 | F6: =F10-F5+F8 -> 1104 | G6: =G4*G7 -> 1041.2628 | H6: =H4*H7 -> 1083.434 | I6: =I4*I7 -> 1179.6322 | J6: =J4*J7 -> 1301.408 | K6: =K4*K7 -> 1575.1968
A7: (% of revenues) | B7: =B6/B4 -> 0.13262811 | C7: =C6/C4 -> 0.10371502 | D7: =D6/D4 -> 0.092805367 | E7: =E6/E4 -> 0.049237691 | F7: =F6/F4 -> 0.11560209 | G7: =AVERAGE(B7:F7) -> 0.098797655 | H7: =AVERAGE(C7:G7) -> 0.092031564 | I7: =AVERAGE(D7:H7) -> 0.089694874 | J7: =AVERAGE(E7:I7) -> 0.089072776 | K7: =AVERAGE(F7:J7) -> 0.097039793
A8: Depreciation | B8: ='Financial Statements'!B15 -> 254.65 | C8: ='Financial Statements'!C15 -> 310.55 | D8: ='Financial Statements'!D15 -> 342 | E8: ='Financial Statements'!E15 -> 376 | F8: ='Financial Statements'!F15 -> 401 | G8: =G9*(G5+(G6*0.5)) -> 446.698 | H8: =H9*(H5+(H6*0.5)) -> 493.46753 | I8: =I9*(I5+(I6*0.5)) -> 545.19101 | J8: =J9*(J5+(J6*0.5)) -> 595.92882 | K8: =K9*(K5+(K6*0.5)) -> 658.35324
A9: (Depreceiation Rate %) | B9: =B8/(B5+(B6*0.5)) -> 0.072784801 | C9: =C8/(C5+(C6*0.5)) -> 0.074557081 | D9: =D8/(D5+(D6*0.5)) -> 0.072905797 | E9: =E8/(E5+(E6*0.5)) -> 0.076484947 | F9: =F8/(F5+(F6*0.5)) -> 0.075817735 | G9: =AVERAGE(C9:F9) -> 0.07494139 | H9: =AVERAGE(D9:G9) -> 0.075037467 | I9: =AVERAGE(E9:H9) -> 0.075570385 | J9: =AVERAGE(F9:I9) -> 0.075341744 | K9: =AVERAGE(G9:J9) -> 0.075222747
A10: Ending PP&E | B10: ='Financial Statements'!B49 -> 3699.01 | C10: ='Financial Statements'!C49 -> 4320.97 | D10: ='Financial Statements'!D49 -> 4719 | E10: ='Financial Statements'!E49 -> 4737 | F10: ='Financial Statements'!F49 -> 5440 | G10: =G5+G6-G8 -> 6034.5648 | H10: =H5+H6-H8 -> 6624.5312 | I10: =I5+I6-I8 -> 7258.9725 | J10: =J5+J6-J8 -> 7964.4516 | K10: =K5+K6-K8 -> 8881.2952

Sheet Beta
A1: BETA CALCULATION | L1: Table of Contents
A3: Divis Laboratories | E3: BSE SENSEX | I3: BETA
A5: Date | B5: Share Price | C5: Return % | E5: Date | F5: Index | G5: Return % | I5: 5 yrs BETA calculation
A6: 44281 | B6: 3464.95 | E6: 44281 | F6: 48969.25 | I6: Using SLOPE Function | J6: =SLOPE(C7:C1243,G7:G1243) -> 0.26619621
A7: 44285 | B7: 3584.25 | C7: =(B7-B6)/B6*100 -> 3.4430511 | E7: 44285 | F7: 49331.68 | G7: =(F7-F6)/F6*100 -> 0.74011752
A8: 44286 | B8: 3622.8 | C8: =(B8-B7)/B7*100 -> 1.0755388 | E8: 44286 | F8: 50049.12 | G8: =(F8-F7)/F7*100 -> 1.454319
A9: 44287 | B9: 3616.1 | C9: =(B9-B8)/B8*100 -> -0.18493983 | E9: 44287 | F9: 49868.53 | G9: =(F9-F8)/F8*100 -> -0.36082553
A10: 44291 | B10: 3611.05 | C10: =(B10-B9)/B9*100 -> -0.13965322 | E10: 44291 | F10: 50020.91 | G10: =(F10-F9)/F9*100 -> 0.30556345
A11: 44292 | B11: 3688.1 | C11: =(B11-B10)/B10*100 -> 2.1337284 | E11: 44292 | F11: 49441.13 | G11: =(F11-F10)/F10*100 -> -1.1590753 | I11: PERFORMANCE VS MARKET
A12: 44293 | B12: 3698.95 | C12: =(B12-B11)/B11*100 -> 0.29418942 | E12: 44293 | F12: 49277.09 | G12: =(F12-F11)/F11*100 -> -0.33178853 | I12: Returns | J12: 5Y
A13: 44294 | B13: 3715.15 | C13: =(B13-B12)/B12*100 -> 0.43796212 | E13: 44294 | F13: 49885.26 | G13: =(F13-F12)/F12*100 -> 1.2341841 | I13: Divis Laboratories | J13: =AVERAGE(C7:C1243) -> 0.058826328
A14: 44295 | B14: 3752.35 | C14: =(B14-B13)/B13*100 -> 1.0013055 | E14: 44295 | F14: 49743.39 | G14: =(F14-F13)/F13*100 -> -0.28439262 | I14: BSE Sensex | J14: =AVERAGE(G7:G1243) -> 0.037737236
A15: 44298 | B15: 3779.65 | C15: =(B15-B14)/B14*100 -> 0.72754407 | E15: 44298 | F15: 48956.65 | G15: =(F15-F14)/F14*100 -> -1.5815971
A16: 44299 | B16: 3718.45 | C16: =(B16-B15)/B15*100 -> -1.6191975 | E16: 44299 | F16: 47991.53 | G16: =(F16-F15)/F15*100 -> -1.9713767
A17: 44301 | B17: 3783.4 | C17: =(B17-B16)/B16*100 -> 1.7466955 | E17: 44301 | F17: 48512.77 | G17: =(F17-F16)/F16*100 -> 1.0861083
A18: 44302 | B18: 3821.85 | C18: =(B18-B17)/B17*100 -> 1.0162817 | E18: 44302 | F18: 48935.74 | G18: =(F18-F17)/F17*100 -> 0.87187353
A19: 44305 | B19: 3807.1 | C19: =(B19-B18)/B18*100 -> -0.38593875 | E19: 44305 | F19: 47940.81 | G19: =(F19-F18)/F18*100 -> -2.0331357
A20: 44306 | B20: 3779.7 | C20: =(B20-B19)/B19*100 -> -0.71970791 | E20: 44306 | F20: 48473.04 | G20: =(F20-F19)/F19*100 -> 1.1101815
A21: 44308 | B21: 3755.25 | C21: =(B21-B20)/B20*100 -> -0.64687674 | E21: 44308 | F21: 47501.71 | G21: =(F21-F20)/F20*100 -> -2.0038562
A22: 44309 | B22: 3779.75 | C22: =(B22-B21)/B21*100 -> 0.65241995 | E22: 44309 | F22: 47863.81 | G22: =(F22-F21)/F21*100 -> 0.76228835
A23: 44312 | B23: 3784.35 | C23: =(B23-B22)/B22*100 -> 0.12170117 | E23: 44312 | F23: 48197.37 | G23: =(F23-F22)/F22*100 -> 0.69689396
A24: 44313 | B24: 3908.95 | C24: =(B24-B23)/B23*100 -> 3.2925073 | E24: 44313 | F24: 48424.08 | G24: =(F24-F23)/F23*100 -> 0.47037836
A25: 44314 | B25: 3882.6 | C25: =(B25-B24)/B24*100 -> -0.67409407 | E25: 44314 | F25: 49066.64 | G25: =(F25-F24)/F24*100 -> 1.3269431
A26: 44315 | B26: 3910.85 | C26: =(B26-B25)/B25*100 -> 0.72760521 | E26: 44315 | F26: 50093.86 | G26: =(F26-F25)/F25*100 -> 2.0935202
... A1243: 46104 | B1243: 6013.5 | C1243: =(B1243-B1242)/B1242*100 -> -1.4180328 | E1243: 46104 | F1243: 73732.58 | G1243: =(F1243-F1242)/F1242*100 -> -1.1089148
A1244: 46105 | B1244: 6026 | E1244: 46105 | F1244: 74212.47
A1245: 46106 | B1245: 6014.5 | E1245: 46106 | F1245: 74652.01

Sheet WACC
A1: Weighted Average Cost of Capital
A2: Capital Structure
A3: Total Debt | B3: ='Financial Statements'!F35 -> 2
A4: Total Equity | B4: ='Financial Statements'!F33 -> 14895
A5: Total Mix | B5: =SUM(B3:B4) -> 14897
A6: % of Debt | B6: =B3/B5 -> 0.00013425522
A7: % of Equity | B7: =B4/B5 -> 0.99986574
A8: Debt to Equity | B8: =B3/B4 -> 0.00013427325
A12: Cost of Equity | D12: Cost of Debt
A13: Risk free rate(Rf) | B13: 0.066 | D13: Source | E13: Cost
A14: Beta | B14: =Beta!J6 -> 0.26619621 | D14: Cost of debt* | E14: ='Financial Statements'!F17/'Financial Statements'!F35 -> 1
A15: Market risk premium | B15: 0.0708 | D15: Tax rate | E15: =Assumptions!G27 -> 0.25168
A16: Cost of equity | B16: =B13+B14*B15 -> 0.084846691 | D16: Cost of Debt after tax | E16: =E14*(1+E15) -> 1.25168
A19: WACC
A20: Source | B20: Weight | C20: Cost | D20: Weighted Cost
A21: Debt | B21: =B6 -> 0.00013425522 | C21: =E16 -> 1.25168 | D21: =B21*C21 -> 0.00016804457
A22: Equity | B22: =B7 -> 0.99986574 | C22: =B16 -> 0.084846691 | D22: =B22*C22 -> 0.0848353
A23: WACC | D23: =SUM(D21:D22) -> 0.085003345

Sheet DCF Valuation
A1: DCF VALUATION
A3: Assumptions/Base
A4: Tax Rate | B4: =Sources!C4 -> 0.246
A5: Discount Rate (WACC) | B5: =WACC!D23 -> 0.085003345
A6: Perpetural Growth Rate | B6: =Sources!C8 -> 0.0825
A7: Valuation Date | B7: 44933
A8: Last Fiscal Year End | B8: 44651
A9: Current Market Price | B9: 115.6
A10: Total Shares Outstanding (in Cr.) | B10: ='Financial Statements'!F31 -> 53
A11: Debt (in Cr.) | B11: =WACC!B3 -> 2
A12: Cash (in Cr.) | B12: ='Financial Statements'!F57 -> 3696
A14: Discounted Cash Flows
A15: Year ˃ | B15: 1 | C15: 2 | D15: 3 | E15: 4 | F15: 5 | G15: Perpetuity Growth | J15: Intrinsic Value
A16: Particulars | B16: 2023F | C16: 2024F | D16: 2025F | E16: 2026F | F16: 2027F | G16: Terminal Value | J16: PV of Cash Flows | K16: =SUM(B27:F27) -> 26896.83
A17: EBIT | B17: ='Financial Statements'!G16 -> 7466.0866 | C17: ='Financial Statements'!H16 -> 8315.8684 | D17: ='Financial Statements'!I16 -> 9196.1079 | E17: ='Financial Statements'!J16 -> 10251.277 | F17: ='Financial Statements'!K16 -> 11453.838 | J17: Continuing Value | K17: =G23 -> 3615256.9
A18: Tax Rate | B18: =$B$4 -> 0.246 | C18: =$B$4 -> 0.246 | D18: =$B$4 -> 0.246 | E18: =$B$4 -> 0.246 | F18: =$B$4 -> 0.246 | J18: PV of contuning value | K18: =G27 -> 2404273
A19: NOPAT | B19: =B17*(1-B18) -> 5629.4293 | C19: =C17*(1-C18) -> 6270.1648 | D19: =D17*(1-D18) -> 6933.8653 | E19: =E17*(1-E18) -> 7729.4627 | F19: =F17*(1-F18) -> 8636.1935 | J19: Enterprise Value (in Cr) | K19: =K16+K18 -> 2431169.9
A20: Add- Depreciation | B20: ='Financial Statements'!G15 -> 446.698 | C20: ='Financial Statements'!H15 -> 493.46753 | D20: ='Financial Statements'!I15 -> 545.19101 | E20: ='Financial Statements'!J15 -> 595.92882 | F20: ='Financial Statements'!K15 -> 658.35324 | J20: Less: Debt (in Cr) | K20: =B11 -> 2
A21: Less-Capex | B21: ='PPE '!G6 -> 1041.2628 | C21: ='PPE '!H6 -> 1083.434 | D21: ='PPE '!I6 -> 1179.6322 | E21: ='PPE '!J6 -> 1301.408 | F21: ='PPE '!K6 -> 1575.1968 | J21: Add: Cash (in Cr) | K21: =B12 -> 3696
A22: Less-Net Changes In WC | B22: ='Financial Statements'!G76 -> -368.16126 | C22: ='Financial Statements'!H76 -> -661.30442 | D22: ='Financial Statements'!I76 -> -634.32756 | E22: ='Financial Statements'!J76 -> -656.32616 | F22: ='Financial Statements'!K76 -> -641.14442 | J22: Equity Value (in Cr) | K22: =K19-K20+K21 -> 2434863.9
A23: Free Cash Flows | B23: =B19+B20-B21-B22 -> 5403.0258 | C23: =C19+C20-C21-C22 -> 6341.5027 | D23: =D19+D20-D21-D22 -> 6933.7517 | E23: =E19+E20-E21-E22 -> 7680.3097 | F23: =F19+F20-F21-F22 -> 8360.4944 | G23: =F23*(1+G25)/(G24-G25) -> 3615256.9 | J23: No. of share (in Cr.) | K23: =B10 -> 53
A24: WACC | B24: =$B$5 -> 0.085003345 | C24: =$B$5 -> 0.085003345 | D24: =$B$5 -> 0.085003345 | E24: =$B$5 -> 0.085003345 | F24: =$B$5 -> 0.085003345 | G24: =$B$5 -> 0.085003345 | J24: Intrincsic value of share | K24: =K22/K23 -> 45940.827
A25: Growth | G25: =B6 -> 0.0825 | J25: Current share price | K25: =B9 -> 115.6
A26: Discounting Factor | B26: =1/(1+B24)^B15 -> 0.92165614 | C26: =1/(1+C24)^C15 -> 0.84945005 | D26: =1/(1+D24)^D15 -> 0.78290086 | E26: =1/(1+E24)^E15 -> 0.72156539 | F26: =1/(1+F24)^F15 -> 0.66503517 | G26: =1/(1+G24)^F15 -> 0.66503517 | J26: No of shares | K26: =K23 -> 53
A27: PV of Free Cash Flow | B27: =B23*B26 -> 4979.7319 | C27: =C23*C26 -> 5386.7898 | D27: =D23*D26 -> 5428.4401 | E27: =E23*E26 -> 5541.8457 | F27: =F23*F26 -> 5560.0228 | G27: =G23*G26 -> 2404273 | J27: Market capitalization (in Cr) | K27: =K25*K26 -> 6126.8
A30: Market Value vs Fair Value
A31: CMP | B31: =B9 -> 115.6 | E31: Sensitivity Analysis to terminal year WACC and growth rate
A32: Upside Potential | B32: =B33-B31 -> 45825.227 | G32: WACC
A33: Fair Value | B33: =K24 -> 45940.827 | F33: =K24 -> 45940.827 | G33: 0.1568 | H33: =G33+0.01 -> 0.1668 | I33: =H33+0.01 -> 0.1768 | J33: =I33+0.01 -> 0.1868
A34: Upside Potential % | B34: =B32/B31 -> 396.412 | E34: GROWTH | F34: 0.03 | G34: 1195.7467 | H34: 1126.3786 | I34: 1067.5894 | J34: 1017.2938
A35: Nature | B35: Undervalued | F35: 0.04 | G35: 1255.2253 | H35: 1175.4429 | I35: 1108.5469 | J35: 1051.8379
A36: Recommendation | B36: Strong Buy Signal | F36: 0.05 | G36: 1325.8422 | H36: 1232.9085 | I36: 1155.9646 | J36: 1091.4323
F37: 0.06 | G37: 1411.0494 | H37: 1301.1355 | I37: 1211.5017 | J37: 1137.2719
F38: 0.0702 | G38: 1518.2334 | H38: 1385.2793 | I38: 1278.884 | J38: 1192.1284

Sheet Relative Valuation
A2: RELATIVE VALUATION
A4: Company | B4: Market Data | F4: Financial Data | J4: Valuation Ratios
B5: Price | C5: No. of Shares(in Cr.) | D5: Market Cap (in Cr) | E5: Enterprise value (in Cr) | F5: Sales (in Cr) | G5: EBITDA (in Cr) | H5: EBIT (in Cr) | I5: EPS | J5: P/E | K5: EV/Sales | L5: EV/EBITDA | M5: EV/EBIT
A6: SUN PHARMA | B6: 1700 | C6: 240 | D6: =B6*C6 -> 408000 | E6: 410000 | F6: 52578 | G6: 15272 | H6: 12000 | I6: 45.5 | J6: =B6/I6 -> 37.362637 | K6: =E6/F6 -> 7.7979383 | L6: =E6/G6 -> 26.846517 | M6: =E6/H6 -> 34.166667
A7: DR REDDY | B7: 1200 | C7: 83 | D7: =B7*C7 -> 99600 | E7: 100000 | F7: 32554 | G7: 9213 | H7: 6500 | I7: 68.1 | J7: =B7/I7 -> 17.621145 | K7: =E7/F7 -> 3.0718191 | L7: =E7/G7 -> 10.854228 | M7: =E7/H7 -> 15.384615
A8: CIPLA | B8: 1450 | C8: 807 | D8: =B8*C8 -> 1170150 | E8: 115000 | F8: 27548 | G8: 7128 | H8: 5500 | I8: 65.4 | J8: =B8/I8 -> 22.171254 | K8: =E8/F8 -> 4.1745317 | L8: =E8/G8 -> 16.133558 | M8: =E8/H8 -> 20.909091
A9: Zydus LIFE | B9: 900 | C9: 1006 | D9: =B9*C9 -> 905400 | E9: 88000 | F9: 23242 | G9: 7059 | H9: 5500 | I9: 47.2 | J9: =B9/I9 -> 19.067797 | K9: =E9/F9 -> 3.786249 | L9: =E9/G9 -> 12.466355 | M9: =E9/H9 -> 16
A10: Average Data | J10: =AVERAGE(J6:J9) -> 24.055708 | K10: =AVERAGE(K6:K9) -> 4.7076345 | L10: =AVERAGE(L6:L9) -> 16.575164 | M10: =AVERAGE(M6:M9) -> 21.615093
A11: Median Data | J11: =MEDIAN(J6:J9) -> 20.619525 | K11: =MEDIAN(K6:K9) -> 3.9803904 | L11: =MEDIAN(L6:L9) -> 14.299956 | M11: =MEDIAN(M6:M9) -> 18.454545

Sheet All Ratio Forecast
B2: RATIOS
B4: INR Cr. | C4: 2024 Actual | D4: 2025 Actual | E4: 2026 Forecast | F4: 2027 Forecast | G4: 2028 Forecast | H4: 2029 Forecast | I4: 2030 Forecast
B5: Growth
B6: Operating Income (%) | C6: =('Financial Statements'!E16-'Financial Statements'!D16)/'Financial Statements'!D16*100 -> -1.4556041 | D6: =('Financial Statements'!F16-'Financial Statements'!E16)/'Financial Statements'!E16*100 -> 24.61226 | E6: =('Financial Statements'!G16-'Financial Statements'!F16)/'Financial Statements'!F16*100 -> 10.62508 | F6: =('Financial Statements'!H16-'Financial Statements'!G16)/'Financial Statements'!G16*100 -> 11.38189 | G6: =('Financial Statements'!I16-'Financial Statements'!H16)/'Financial Statements'!H16*100 -> 10.585058 | H6: =('Financial Statements'!J16-'Financial Statements'!I16)/'Financial Statements'!I16*100 -> 11.474082 | I6: =('Financial Statements'!K16-'Financial Statements'!J16)/'Financial Statements'!J16*100 -> 11.730839
B7: EBITDA (%) | C7: =('Financial Statements'!E14-'Financial Statements'!D14)/'Financial Statements'!D14*100 -> -0.78794108 | D7: =('Financial Statements'!F14-'Financial Statements'!E14)/'Financial Statements'!E14*100 -> 23.446133 | E7: =('Financial Statements'!G14-'Financial Statements'!F14)/'Financial Statements'!F14*100 -> 10.668317 | F7: =('Financial Statements'!H14-'Financial Statements'!G14)/'Financial Statements'!G14*100 -> 11.330414 | G7: =('Financial Statements'!I14-'Financial Statements'!H14)/'Financial Statements'!H14*100 -> 10.579264 | H7: =('Financial Statements'!J14-'Financial Statements'!I14)/'Financial Statements'!I14*100 -> 11.352765 | I7: =('Financial Statements'!K14-'Financial Statements'!J14)/'Financial Statements'!J14*100 -> 11.661853
B8: Adj PAT (%) | C8: =('Financial Statements'!E22-'Financial Statements'!D22)/'Financial Statements'!D22*100 -> -1.8593371 | D8: =('Financial Statements'!F22-'Financial Statements'!E22)/'Financial Statements'!E22*100 -> 24.114498 | E8: =('Financial Statements'!G22-'Financial Statements'!F22)/'Financial Statements'!F22*100 -> -7.3372836 | F8: =('Financial Statements'!H22-'Financial Statements'!G22)/'Financial Statements'!G22*100 -> 11.38114 | G8: =('Financial Statements'!I22-'Financial Statements'!H22)/'Financial Statements'!H22*100 -> 10.581648 | H8: =('Financial Statements'!J22-'Financial Statements'!I22)/'Financial Statements'!I22*100 -> 11.472461 | I8: =('Financial Statements'!K22-'Financial Statements'!J22)/'Financial Statements'!J22*100 -> 11.736938
B9: Adj EPS (%) | C9: =('Financial Statements'!E23-'Financial Statements'!D23)/'Financial Statements'!D23*100 -> -1.8593371 | D9: =('Financial Statements'!F23-'Financial Statements'!E23)/'Financial Statements'!E23*100 -> 24.114498 | E9: =('Financial Statements'!G23-'Financial Statements'!F23)/'Financial Statements'!F23*100 -> -7.3372836 | F9: =('Financial Statements'!H23-'Financial Statements'!G23)/'Financial Statements'!G23*100 -> 11.38114 | G9: =('Financial Statements'!I23-'Financial Statements'!H23)/'Financial Statements'!H23*100 -> 10.581648 | H9: =('Financial Statements'!J23-'Financial Statements'!I23)/'Financial Statements'!I23*100 -> 11.472461 | I9: =('Financial Statements'!K23-'Financial Statements'!J23)/'Financial Statements'!J23*100 -> 11.736938
B11: Profitability
B12: EBITDA Margin (%) | C12: ='Financial Statements'!E14/'Financial Statements'!E9*100 -> 72.381905 | D12: ='Financial Statements'!F14/'Financial Statements'!F9*100 -> 74.86911 | E12: ='Financial Statements'!G14/'Financial Statements'!G9*100 -> 75.078508 | F12: ='Financial Statements'!H14/'Financial Statements'!H9*100 -> 74.830306 | G12: ='Financial Statements'!I14/'Financial Statements'!I9*100 -> 74.069235 | H12: ='Financial Statements'!J14/'Financial Statements'!J9*100 -> 74.241953 | I12: ='Financial Statements'!K14/'Financial Statements'!K9*100 -> 74.616992
B13: Operating Income | C13: ='Financial Statements'!E16 -> 5416 | D13: ='Financial Statements'!F16 -> 6749 | E13: ='Financial Statements'!G16 -> 7466.0866 | F13: ='Financial Statements'!H16 -> 8315.8684 | G13: ='Financial Statements'!I16 -> 9196.1079 | H13: ='Financial Statements'!J16 -> 10251.277 | I13: ='Financial Statements'!K16 -> 11453.838
B14: EBIT Margin (%) | C14: ='Financial Statements'!E16/'Financial Statements'!E9*100 -> 67.683079 | D14: ='Financial Statements'!F16/'Financial Statements'!F9*100 -> 70.670157 | E14: ='Financial Statements'!G16/'Financial Statements'!G9*100 -> 70.840124 | F14: ='Financial Statements'!H16/'Financial Statements'!H9*100 -> 70.638579 | G14: ='Financial Statements'!I16/'Financial Statements'!I9*100 -> 69.923805 | H14: ='Financial Statements'!J16/'Financial Statements'!J9*100 -> 70.163214 | I14: ='Financial Statements'!K16/'Financial Statements'!K9*100 -> 70.561216
B15: PAT | C15: ='Financial Statements'!E22 -> 4856 | D15: ='Financial Statements'!F22 -> 6027 | E15: ='Financial Statements'!G22 -> 5584.7819 | F15: ='Financial Statements'!H22 -> 6220.3938 | G15: ='Financial Statements'!I22 -> 6878.614 | H15: ='Financial Statements'!J22 -> 7667.7602 | I15: ='Financial Statements'!K22 -> 8567.7205
B16: PAT Margin (%) | C16: ='Financial Statements'!E22/'Financial Statements'!E9*100 -> 60.684829 | D16: ='Financial Statements'!F22/'Financial Statements'!F9*100 -> 63.109948 | E16: ='Financial Statements'!G22/'Financial Statements'!G9*100 -> 52.989828 | F16: ='Financial Statements'!H22/'Financial Statements'!H9*100 -> 52.838712 | G16: ='Financial Statements'!I22/'Financial Statements'!I9*100 -> 52.302438 | H16: ='Financial Statements'!J22/'Financial Statements'!J9*100 -> 52.48075 | I16: ='Financial Statements'!K22/'Financial Statements'!K9*100 -> 52.78133
B17: ROE (%) | C17: ='Financial Statements'!E22/'Financial Statements'!E33*100 -> 36.013053 | D17: ='Financial Statements'!F22/'Financial Statements'!F33*100 -> 40.463243 | E17: ='Financial Statements'!G22/'Financial Statements'!G33*100 -> 27.269733 | F17: ='Financial Statements'!H22/'Financial Statements'!H33*100 -> 23.297202 | G17: ='Financial Statements'!I22/'Financial Statements'!I33*100 -> 20.484997 | H17: ='Financial Statements'!J22/'Financial Statements'!J33*100 -> 18.590065 | I17: ='Financial Statements'!K22/'Financial Statements'!K33*100 -> 17.19933
B18: ROCE (%) | C18: ='Financial Statements'!E16/('Financial Statements'!E61-'Financial Statements'!E45)*100 -> 44.168977 | D18: ='Financial Statements'!F16/('Financial Statements'!F61-'Financial Statements'!F45)*100 -> 50.07048 | E18: ='Financial Statements'!G16/('Financial Statements'!G61-'Financial Statements'!G45)*100 -> 39.466164 | F18: ='Financial Statements'!H16/('Financial Statements'!H61-'Financial Statements'!H45)*100 -> 33.269034 | G18: ='Financial Statements'!I16/('Financial Statements'!I61-'Financial Statements'!I45)*100 -> 29.053003 | H18: ='Financial Statements'!J16/('Financial Statements'!J61-'Financial Statements'!J45)*100 -> 26.225085 | I18: ='Financial Statements'!K16/('Financial Statements'!K61-'Financial Statements'!K45)*100 -> 24.140371
B20: Valuations
B21: Price-earnings | C21: ='DCF Valuation'!$B$9/'Financial Statements'!E23 -> 1.2616969 | D21: ='DCF Valuation'!$B$9/'Financial Statements'!F23 -> 1.0165588 | E21: ='DCF Valuation'!$B$9/'Financial Statements'!G23 -> 1.0970527 | F21: ='DCF Valuation'!$B$9/'Financial Statements'!H23 -> 0.98495372 | G21: ='DCF Valuation'!$B$9/'Financial Statements'!I23 -> 0.8907027 | H21: ='DCF Valuation'!$B$9/'Financial Statements'!J23 -> 0.79903385 | I21: ='DCF Valuation'!$B$9/'Financial Statements'!K23 -> 0.71510269
B22: Price-book | C22: ='DCF Valuation'!$B$9/('Financial Statements'!E33/'Financial Statements'!E31) -> 0.45437556 | D22: ='DCF Valuation'!$B$9/('Financial Statements'!F33/'Financial Statements'!F31) -> 0.41133266 | E22: ='DCF Valuation'!$B$9/('Financial Statements'!G33/'Financial Statements'!G31) -> 0.29916334 | F22: ='DCF Valuation'!$B$9/('Financial Statements'!H33/'Financial Statements'!H31) -> 0.22946665 | G22: ='DCF Valuation'!$B$9/('Financial Statements'!I33/'Financial Statements'!I31) -> 0.18246042 | H22: ='DCF Valuation'!$B$9/('Financial Statements'!J33/'Financial Statements'!J31) -> 0.14854091 | I22: ='DCF Valuation'!$B$9/('Financial Statements'!K33/'Financial Statements'!K31) -> 0.12299287
B23: EV/EBITDA | C23: ='DCF Valuation'!$K$19/'Financial Statements'!E14 -> 419.74618 | D23: ='DCF Valuation'!$K$19/'Financial Statements'!F14 -> 340.02376 | E23: ='DCF Valuation'!$K$19/'Financial Statements'!G14 -> 307.2458 | F23: ='DCF Valuation'!$K$19/'Financial Statements'!H14 -> 275.97652 | G23: ='DCF Valuation'!$K$19/'Financial Statements'!I14 -> 249.57348 | H23: ='DCF Valuation'!$K$19/'Financial Statements'!J14 -> 224.12868 | I23: ='DCF Valuation'!$K$19/'Financial Statements'!K14 -> 200.7209
B24: EV/Sales | C24: ='DCF Valuation'!$K$19/'Financial Statements'!E9 -> 303.82028 | D24: ='DCF Valuation'!$K$19/'Financial Statements'!F9 -> 254.57276 | E24: ='DCF Valuation'!$K$19/'Financial Statements'!G9 -> 230.67556 | F24: ='DCF Valuation'!$K$19/'Financial Statements'!H9 -> 206.51407 | G24: ='DCF Valuation'!$K$19/'Financial Statements'!I9 -> 184.85717 | H24: ='DCF Valuation'!$K$19/'Financial Statements'!J9 -> 166.39751 | I24: ='DCF Valuation'!$K$19/'Financial Statements'!K9 -> 149.7719
B25: Dividend payout ratio (%) | C25: ='Financial Statements'!E24/'Financial Statements'!E22*100 -> 0 | D25: ='Financial Statements'!F24/'Financial Statements'!F22*100 -> 0 | E25: ='Financial Statements'!G24/'Financial Statements'!G22*100 -> 0 | F25: ='Financial Statements'!H24/'Financial Statements'!H22*100 -> 0 | G25: ='Financial Statements'!I24/'Financial Statements'!I22*100 -> 0 | H25: ='Financial Statements'!J24/'Financial Statements'!J22*100 -> 0 | I25: ='Financial Statements'!K24/'Financial Statements'!K22*100 -> 0
B26: Dividend yield (%) | C26: =('Financial Statements'!E24/'Financial Statements'!E31)/'DCF Valuation'!$B$9*100 -> 0 | D26: =('Financial Statements'!F24/'Financial Statements'!F31)/'DCF Valuation'!$B$9*100 -> 0 | E26: =('Financial Statements'!G24/'Financial Statements'!G31)/'DCF Valuation'!$B$9*100 -> 0 | F26: =('Financial Statements'!H24/'Financial Statements'!H31)/'DCF Valuation'!$B$9*100 -> 0 | G26: =('Financial Statements'!I24/'Financial Statements'!I31)/'DCF Valuation'!$B$9*100 -> 0 | H26: =('Financial Statements'!J24/'Financial Statements'!J31)/'DCF Valuation'!$B$9*100 -> 0 | I26: =('Financial Statements'!K24/'Financial Statements'!K31)/'DCF Valuation'!$B$9*100 -> 0
B28: B/S ratios
B29: Inventory days | C29: =Assumptions!E38 -> 1404.0271 | D29: =Assumptions!F38 -> 1493.9879 | E29: =Assumptions!G38 -> 1424.5642 | F29: =Assumptions!H38 -> 1423.5054 | G29: =Assumptions!I38 -> 1409.1567 | H29: =Assumptions!J38 -> 1431.0482 | I29: =Assumptions!K38 -> 1436.4525
B30: Debtor days | C30: =Assumptions!E35 -> 108.2381 | D30: =Assumptions!F35 -> 113.29365 | E30: =Assumptions!G35 -> 102.97902 | F30: =Assumptions!H35 -> 104.8319 | G30: =Assumptions!I35 -> 104.67142 | H30: =Assumptions!J35 -> 106.80282 | I30: =Assumptions!K35 -> 106.51576
B31: Asset turnover | C31: ='Financial Statements'!E9/'Financial Statements'!E61 -> 0.59182013 | D31: ='Financial Statements'!F9/'Financial Statements'!F61 -> 0.64106867 | E31: ='Financial Statements'!G9/'Financial Statements'!G61 -> 0.51457177 | F31: ='Financial Statements'!H9/'Financial Statements'!H61 -> 0.44087968 | G31: ='Financial Statements'!I9/'Financial Statements'!I61 -> 0.39164331 | H31: ='Financial Statements'!J9/'Financial Statements'!J61 -> 0.35421295 | I31: ='Financial Statements'!K9/'Financial Statements'!K61 -> 0.32585215
B32: Current ratio | C32: ='Financial Statements'!E60/'Financial Statements'!E45 -> 7.6028594 | D32: ='Financial Statements'!F60/'Financial Statements'!F45 -> 7.0373766 | E32: ='Financial Statements'!G60/'Financial Statements'!G45 -> 9.6639507 | F32: ='Financial Statements'!H60/'Financial Statements'!H45 -> 12.241699 | G32: ='Financial Statements'!I60/'Financial Statements'!I45 -> 14.189456 | H32: ='Financial Statements'!J60/'Financial Statements'!J45 -> 16.004529 | I32: ='Financial Statements'!K60/'Financial Statements'!K45 -> 17.903241
B33: Debt/equity | C33: =('Financial Statements'!E40+'Financial Statements'!E42)/'Financial Statements'!E33 -> 0.045906259 | D33: =('Financial Statements'!F40+'Financial Statements'!F42)/'Financial Statements'!F33 -> 0.034441088 | E33: =('Financial Statements'!G40+'Financial Statements'!G42)/'Financial Statements'!G33 -> 0.025049095 | F33: =('Financial Statements'!H40+'Financial Statements'!H42)/'Financial Statements'!H33 -> 0.019213357 | G33: =('Financial Statements'!I40+'Financial Statements'!I42)/'Financial Statements'!I33 -> 0.015277501 | H33: =('Financial Statements'!J40+'Financial Statements'!J42)/'Financial Statements'!J33 -> 0.012437404 | I33: =('Financial Statements'!K40+'Financial Statements'!K42)/'Financial Statements'!K33 -> 0.010298254
B34: Interest Coverage ratio | C34: ='Financial Statements'!E16/'Financial Statements'!E17 -> 1354 | D34: ='Financial Statements'!F16/'Financial Statements'!F17 -> 3374.5 | E34: ='Financial Statements'!G16/'Financial Statements'!G17 -> 2494.1714 | F34: ='Financial Statements'!H16/'Financial Statements'!H17 -> 2452.993 | G34: ='Financial Statements'!I16/'Financial Statements'!I17 -> 2280.5913 | H34: ='Financial Statements'!J16/'Financial Statements'!J17 -> 2207.3857 | I34: ='Financial Statements'!K16/'Financial Statements'!K17 -> 2509.6781

Sheet Key Ratio Forecast
B2: KEY FORECAST
B4: INR Cr. | C4: 2025 Actual | D4: 2026 Forecast | E4: 2027 Forecast | F4: 2028 Forecast | G4: 2029 Forecast | H4: 2030 Forecast
B5: Operating Income | C5: ='Financial Statements'!F16 -> 6749 | D5: ='Financial Statements'!G16 -> 7466.0866 | E5: ='Financial Statements'!H16 -> 8315.8684 | F5: ='Financial Statements'!I16 -> 9196.1079 | G5: ='Financial Statements'!J16 -> 10251.277 | H5: ='Financial Statements'!K16 -> 11453.838
B6: EBIT Growth | C6: =(C5-'Financial Statements'!E16)/'Financial Statements'!E16 -> 0.2461226 | D6: =(D5-C5)/C5 -> 0.1062508 | E6: =(E5-D5)/D5 -> 0.1138189 | F6: =(F5-E5)/E5 -> 0.10585058 | G6: =(G5-F5)/F5 -> 0.11474082 | H6: =(H5-G5)/G5 -> 0.11730839
B7: EBITDA | C7: ='Financial Statements'!F14 -> 7150 | D7: ='Financial Statements'!G14 -> 7912.7846 | E7: ='Financial Statements'!H14 -> 8809.3359 | F7: ='Financial Statements'!I14 -> 9741.2989 | G7: ='Financial Statements'!J14 -> 10847.206 | H7: ='Financial Statements'!K14 -> 12112.191
B8: EBITDA Margin (%) | C8: =C7/'Financial Statements'!F9 -> 0.7486911 | D8: =D7/'Financial Statements'!G9 -> 0.75078508 | E8: =E7/'Financial Statements'!H9 -> 0.74830306 | F8: =F7/'Financial Statements'!I9 -> 0.74069235 | G8: =G7/'Financial Statements'!J9 -> 0.74241953 | H8: =H7/'Financial Statements'!K9 -> 0.74616992
B9: Net Income | C9: ='Financial Statements'!F22 -> 6027 | D9: ='Financial Statements'!G22 -> 5584.7819 | E9: ='Financial Statements'!H22 -> 6220.3938 | F9: ='Financial Statements'!I22 -> 6878.614 | G9: ='Financial Statements'!J22 -> 7667.7602 | H9: ='Financial Statements'!K22 -> 8567.7205
B10: EPS | C10: ='Financial Statements'!F23 -> 113.71698 | D10: ='Financial Statements'!G23 -> 105.37324 | E10: ='Financial Statements'!H23 -> 117.36592 | F10: ='Financial Statements'!I23 -> 129.78517 | G10: ='Financial Statements'!J23 -> 144.67472 | H10: ='Financial Statements'!K23 -> 161.6551
B11: EPS Growth (%) | C11: =(C10-'Financial Statements'!E23)/'Financial Statements'!E23*100 -> 24.114498 | D11: =(D10-C10)/C10*100 -> -7.3372836 | E11: =(E10-D10)/D10*100 -> 11.38114 | F11: =(F10-E10)/E10*100 -> 10.581648 | G11: =(G10-F10)/F10*100 -> 11.472461 | H11: =(H10-G10)/G10*100 -> 11.736938
B12: Dividend yield (%) | C12: =('Financial Statements'!F24/'Financial Statements'!F31)/'DCF Valuation'!$B$9*100 -> 0 | D12: =('Financial Statements'!G24/'Financial Statements'!G31)/'DCF Valuation'!$B$9*100 -> 0 | E12: =('Financial Statements'!H24/'Financial Statements'!H31)/'DCF Valuation'!$B$9*100 -> 0 | F12: =('Financial Statements'!I24/'Financial Statements'!I31)/'DCF Valuation'!$B$9*100 -> 0 | G12: =('Financial Statements'!J24/'Financial Statements'!J31)/'DCF Valuation'!$B$9*100 -> 0 | H12: =('Financial Statements'!K24/'Financial Statements'!K31)/'DCF Valuation'!$B$9*100 -> 0
B13: ROCE (%) | C13: ='Financial Statements'!F16/('Financial Statements'!F61-'Financial Statements'!F45) -> 0.5007048 | D13: ='Financial Statements'!G16/('Financial Statements'!G61-'Financial Statements'!G45) -> 0.39466164 | E13: ='Financial Statements'!H16/('Financial Statements'!H61-'Financial Statements'!H45) -> 0.33269034 | F13: ='Financial Statements'!I16/('Financial Statements'!I61-'Financial Statements'!I45) -> 0.29053003 | G13: ='Financial Statements'!J16/('Financial Statements'!J61-'Financial Statements'!J45) -> 0.26225085 | H13: ='Financial Statements'!K16/('Financial Statements'!K61-'Financial Statements'!K45) -> 0.24140371
B14: ROE (%) | C14: ='Financial Statements'!F22/'Financial Statements'!F33 -> 0.40463243 | D14: ='Financial Statements'!G22/'Financial Statements'!G33 -> 0.27269733 | E14: ='Financial Statements'!H22/'Financial Statements'!H33 -> 0.23297202 | F14: ='Financial Statements'!I22/'Financial Statements'!I33 -> 0.20484997 | G14: ='Financial Statements'!J22/'Financial Statements'!J33 -> 0.18590065 | H14: ='Financial Statements'!K22/'Financial Statements'!K33 -> 0.1719933
B15: PE | C15: ='DCF Valuation'!$B$9/'Financial Statements'!F23 -> 1.0165588 | D15: ='DCF Valuation'!$B$9/'Financial Statements'!G23 -> 1.0970527 | E15: ='DCF Valuation'!$B$9/'Financial Statements'!H23 -> 0.98495372 | F15: ='DCF Valuation'!$B$9/'Financial Statements'!I23 -> 0.8907027 | G15: ='DCF Valuation'!$B$9/'Financial Statements'!J23 -> 0.79903385 | H15: ='DCF Valuation'!$B$9/'Financial Statements'!K23 -> 0.71510269
B16: P/BV | C16: ='DCF Valuation'!$B$9/('Financial Statements'!F33/'Financial Statements'!F31) -> 0.41133266 | D16: ='DCF Valuation'!$B$9/('Financial Statements'!G33/'Financial Statements'!G31) -> 0.29916334 | E16: ='DCF Valuation'!$B$9/('Financial Statements'!H33/'Financial Statements'!H31) -> 0.22946665 | F16: ='DCF Valuation'!$B$9/('Financial Statements'!I33/'Financial Statements'!I31) -> 0.18246042 | G16: ='DCF Valuation'!$B$9/('Financial Statements'!J33/'Financial Statements'!J31) -> 0.14854091 | H16: ='DCF Valuation'!$B$9/('Financial Statements'!K33/'Financial Statements'!K31) -> 0.12299287
B17: PE at Fair Value | C17: ='DCF Valuation'!$B$33/'Financial Statements'!F23 -> 403.99268 | D17: ='DCF Valuation'!$B$33/'Financial Statements'!G23 -> 435.9819 | E17: ='DCF Valuation'!$B$33/'Financial Statements'!H23 -> 391.43243 | F17: ='DCF Valuation'!$B$33/'Financial Statements'!I23 -> 353.97594 | G17: ='DCF Valuation'!$B$33/'Financial Statements'!J23 -> 317.54564 | H17: ='DCF Valuation'!$B$33/'Financial Statements'!K23 -> 284.19039

Sheet Sheet15
A3: Sum of Revenue Growth | B3: Column Labels
A4: Row Labels | B4: Cipla | C4: Divis Lab | D4: Dr Reddy | E4: Sun Pharma | F4: Grand Total
A5: 2021 | B5: 0 | C5: 0 | D5: 29.5 | E5: 0 | F5: 29.5
A6: 2022 | B6: 119.77 | C6: 30.61 | D6: 21.35 | E6: 27.22 | F6: 198.95
A7: 2023 | B7: 18.28 | C7: -14.13 | D7: 28.33 | E7: 13.89 | F7: 46.37
A8: 2024 | B8: 5.31 | C8: 0.52 | D8: 34.84 | E8: 14.13 | F8: 54.8
A9: 2025 | B9: 16.89 | C9: 20 | D9: 36.28 | E9: 5.14 | F9: 78.31
A10: Grand Total | B10: 160.25 | C10: 37 | D10: 150.3 | E10: 60.38 | F10: 407.93
A13: Sum of EBITDA Margin | B13: Column Labels
A14: Row Labels | B14: Cipla | C14: Divis Lab | D14: Dr Reddy | E14: Sun Pharma | F14: Grand Total
A15: 2021 | B15: -19.08 | C15: 46.17 | D15: 16.38 | E15: 56.66 | F15: 100.13
A16: 2022 | B16: 7.57 | C16: 48.42 | D16: 11.27 | E16: 59.45 | F16: 126.71
A17: 2023 | B17: 13.07 | C17: 39.87 | D17: 15.4 | E17: 11.23 | F17: 79.57
A18: 2024 | B18: 13.03 | C18: 37.68 | D18: 22.29 | E18: 63.17 | F18: 136.17
A19: 2025 | B19: 15.19 | C19: 40.58 | D19: 23.14 | E19: 67.94 | F19: 146.85
A20: Grand Total | B20: 29.78 | C20: 212.72 | D20: 88.48 | E20: 258.45 | F20: 589.43
A23: Sum of Interest Coverage Ratio | B23: Column Labels
A24: Row Labels | B24: Cipla | C24: Divis Lab | D24: Dr Reddy | E24: Sun Pharma | F24: Grand Total
A25: 2021 | B25: -191.76 | C25: 1734.24 | D25: 84.32 | E25: 0 | F25: 1626.8
A26: 2022 | B26: 141.09 | C26: 2485.17 | D26: 80.95 | E26: 145.61 | F26: 2852.82
A27: 2023 | B27: 16.5 | C27: 1520 | D27: 284.38 | E27: 65.63 | F27: 1886.51
A28: 2024 | B28: 18.14 | C28: 722 | D28: 311.41 | E28: 353.89 | F28: 1405.44
A29: 2025 | B29: 59.86 | C29: 1866.5 | D29: 76.3 | E29: 4083.95 | F29: 6086.61
A30: Grand Total | B30: 43.83 | C30: 8327.91 | D30: 837.36 | E30: 4649.08 | F30: 13858.18
A33: Sum of Current Ratio | B33: Column Labels
A34: Row Labels | B34: Cipla | C34: Divis Lab | D34: Dr Reddy | E34: Sun Pharma | F34: Grand Total
A35: 2021 | B35: 1.4 | C35: 5.63 | D35: 2.4 | E35: 2.58 | F35: 12.01
A36: 2022 | B36: 1.48 | C36: 7.1 | D36: 2.23 | E36: 2.31 | F36: 13.12
A37: 2023 | B37: 1.63 | C37: 8.56 | D37: 3.11 | E37: 2.95 | F37: 16.25
A38: 2024 | B38: 1.97 | C38: 7.6 | D38: 3.22 | E38: 2.64 | F38: 15.43
A39: 2025 | B39: 1.82 | C39: 7.04 | D39: 1.91 | E39: 9.24 | F39: 20.01
A40: Grand Total | B40: 8.3 | C40: 35.93 | D40: 12.87 | E40: 19.72 | F40: 76.82

Sheet Peer Comparison
B3: Company Name | C3: Year | D3: Revenue Growth | E3: EBITDA Margin | F3: Return on Assets | G3: Return on Equity | H3: Current Ratio | I3: Debt/Equity Ratio | J3: Interest Coverage Ratio | K3: Asset Turnover
B4: Divis Lab | C4: 2021 | D4: — | E4: 46.17 | F4: 21.02 | G4: 21.08 | H4: 5.63 | I4: 0 | J4: 1734.24 | K4: 0.73
B5: Divis Lab | C5: 2022 | D5: 30.61 | E5: 48.42 | F5: 25.16 | G5: 25.22 | H5: 7.1 | I5: 0 | J5: 2485.17 | K5: 0.76
B6: Divis Lab | C6: 2023 | D6: -14.13 | E6: 39.87 | F6: 14.2 | G6: 14.23 | H6: 8.56 | I6: 0 | J6: 1520 | K6: 0.6
B7: Divis Lab | C7: 2024 | D7: 0.52 | E7: 37.68 | F7: 11.66 | G7: 11.69 | H7: 7.6 | I7: 0 | J7: 722 | K7: 0.57
B8: Divis Lab | C8: 2025 | D8: 20 | E8: 40.58 | F8: 14.83 | G8: 14.83 | H8: 7.04 | I8: 0 | J8: 1866.5 | K8: 0.62
B9: Dr Reddy | C9: 2021 | D9: 29.5 | E9: 16.38 | F9: 10.11 | G9: 12.87 | H9: 2.4 | I9: 0.07 | J9: 84.32 | K9: 0.62
B10: Dr Reddy | C10: 2022 | D10: 21.35 | E10: 11.27 | F10: 6.63 | G10: 8.85 | H10: 2.23 | I10: 0.12 | J10: 80.95 | K10: 0.59
B11: Dr Reddy | C11: 2023 | D11: 28.33 | E11: 15.4 | F11: 10.3 | G11: 12.76 | H11: 3.11 | I11: 0 | J11: 284.38 | K11: 0.67
B12: Dr Reddy | C12: 2024 | D12: 34.84 | E12: 22.29 | F12: 14.3 | G12: 17.91 | H12: 3.22 | I12: 0.03 | J12: 311.41 | K12: 0.64
B13: Dr Reddy | C13: 2025 | D13: 36.28 | E13: 23.14 | F13: 13.97 | G13: 18.54 | H13: 1.91 | I13: 0.12 | J13: 76.3 | K13: 0.6
B14: Cipla | C14: 2021 | D14: — | E14: -19.08 | F14: -16.06 | G14: -44.02 | H14: 1.4 | I14: 0 | J14: -191.76 | K14: 1.42
B15: Cipla | C15: 2022 | D15: 119.77 | E15: 7.57 | F15: 5.3 | G15: 23.77 | H15: 1.48 | I15: 0 | J15: 141.09 | K15: 2.22
B16: Cipla | C16: 2023 | D16: 18.28 | E16: 13.07 | F16: 8.52 | G16: 50.55 | H16: 1.63 | I16: 0.77 | J16: 16.5 | K16: 1.84
B17: Cipla | C17: 2024 | D17: 5.31 | E17: 13.03 | F17: 8.26 | G17: 31.71 | H17: 1.97 | I17: 0.18 | J17: 18.14 | K17: 1.94
B18: Cipla | C18: 2025 | D18: 16.89 | E18: 15.19 | F18: 9.7 | G18: 28.85 | H18: 1.82 | I18: 0 | J18: 59.86 | K18: 1.77
B19: Sun Pharma | C19: 2021 | D19: — | E19: 56.66 | F19: 8.02 | G19: 8.32 | H19: 2.58 | I19: 0.03 | J19: — | K19: 0.3
B20: Sun Pharma | C20: 2022 | D20: 27.22 | E20: 59.45 | F20: 8.02 | G20: 11.32 | H20: 2.31 | I20: 0.02 | J20: 145.61 | K20: 0.34
B21: Sun Pharma | C21: 2023 | D21: 13.89 | E21: 11.23 | F21: -5.58 | G21: -5.66 | H21: 2.95 | I21: 0.01 | J21: 65.63 | K21: 0.41
B22: Sun Pharma | C22: 2024 | D22: 14.13 | E22: 63.17 | F22: 16.45 | G22: 16.53 | H22: 2.64 | I22: 0 | J22: 353.89 | K22: 0.4
B23: Sun Pharma | C23: 2025 | D23: 5.14 | E23: 67.94 | F23: 17.96 | G23: 18.02 | H23: 9.24 | I23: 0 | J23: 4083.95 | K23: 0.34

Sheet Dashboard
H6: Peer Comparision Dashboard

Sheet Sheet7
A3: Sum of Revenue Growth | B3: Column Labels
A4: Row Labels | B4: Hindalco | C4: Jindal Steel | D4: JSW Steel | E4: Tata Steel | F4: Grand Total
A5: 2018 | B5: 0.159 | C5: 0.2323 | D5: 0.2711 | E5: 0.2422 | F5: 0.9046
A6: 2019 | B6: 0.0687 | C6: 0.6241 | D6: 0.1613 | E6: 0.1844 | F6: 1.0385
A7: 2020 | B7: -0.1204 | C7: -0.0537 | D7: -0.1675 | E7: -0.1441 | F7: -0.4857
A8: 2021 | B8: 0.0611 | C8: 0.2699 | D8: 0.1006 | E8: 0.3921 | F8: 0.8237
A9: 2022 | B9: 0.5843 | C9: 0.4841 | D9: 0.68 | E9: 0.5335 | F9: 2.2819
A10: Grand Total | B10: 0.7527 | C10: 1.5567 | D10: 1.0455 | E10: 1.2081 | F10: 4.563

Sheet Sheet8
A3: Sum of EBITDA Margin | B3: Column Labels
A4: Row Labels | B4: Hindalco | C4: Jindal Steel | D4: JSW Steel | E4: Tata Steel | F4: Grand Total
A5: 2018 | B5: 0.1087 | C5: 0.173 | D5: 0.2029 | E5: 0.2587 | F5: 0.7433
A6: 2019 | B6: 0.0877 | C6: 0.1514 | D6: 0.2398 | E6: 0.2912 | F6: 0.7701
A7: 2020 | B7: 0.0893 | C7: 0.1519 | D7: 0.1897 | E7: 0.2459 | F7: 0.6768
A8: 2021 | B8: 0.0888 | C8: 0.2742 | D8: 0.2717 | E8: 0.3224 | F8: 0.9571
A9: 2022 | B9: 0.1629 | C9: 0.1963 | D9: 0.2646 | E9: 0.3963 | F9: 1.0201
A10: Grand Total | B10: 0.5374 | C10: 0.9468 | D10: 1.1687 | E10: 1.5145 | F10: 4.1674

Sheet Sheet9
A3: Sum of Return on Assets | B3: Column Labels
A4: Row Labels | B4: Hindalco | C4: Jindal Steel | D4: JSW Steel | E4: Tata Steel | F4: Grand Total
A5: 2018 | B5: 0.0173 | C5: -0.006 | D5: 0.054 | E5: 0.0333 | F5: 0.0986
A6: 2019 | B6: 0.0147 | C6: -0.0045 | D6: 0.0755 | E6: 0.0766 | F6: 0.1623
A7: 2020 | B7: 0.0077 | C7: 0.0104 | D7: 0.0433 | E7: 0.0448 | F7: 0.1062
A8: 2021 | B8: 0.0112 | C8: 0.1034 | D8: 0.0629 | E8: 0.0946 | F8: 0.2721
A9: 2022 | B9: 0.0555 | C9: 0.1102 | D9: 0.1025 | E9: 0.1487 | F9: 0.4169
A10: Grand Total | B10: 0.1064 | C10: 0.2135 | D10: 0.3382 | E10: 0.398 | F10: 1.0561

Sheet Sheet10
A3: Sum of Return on Equity | B3: Column Labels
A4: Row Labels | B4: Hindalco | C4: Jindal Steel | D4: JSW Steel | E4: Tata Steel | F4: Grand Total
A5: 2018 | B5: 0.029 | C5: -0.0158 | D5: 0.1657 | E5: 0.0677 | F5: 0.2466
A6: 2019 | B6: 0.0248 | C6: -0.0116 | D6: 0.2327 | E6: 0.1495 | F6: 0.3954
A7: 2020 | B7: 0.0136 | C7: 0.026 | D7: 0.1379 | E7: 0.0904 | F7: 0.2679
A8: 2021 | B8: 0.0198 | C8: 0.2191 | D8: 0.1786 | E8: 0.1808 | F8: 0.5983
A9: 2022 | B9: 0.1011 | C9: 0.2052 | D9: 0.263 | E9: 0.2631 | F9: 0.8324
A10: Grand Total | B10: 0.1883 | C10: 0.4229 | D10: 0.9779 | E10: 0.7515 | F10: 2.3406

Sheet Sheet11
A3: Sum of Current Ratio | B3: Column Labels
A4: Row Labels | B4: Hindalco | C4: Jindal Steel | D4: JSW Steel | E4: Tata Steel | F4: Grand Total
A5: 2018 | B5: 1.7 | C5: 0.62 | D5: 0.76 | E5: 1.35 | F5: 4.43
A6: 2019 | B6: 1.68 | C6: 0.58 | D6: 0.78 | E6: 0.67 | F6: 3.71
A7: 2020 | B7: 1.58 | C7: 0.74 | D7: 0.83 | E7: 0.65 | F7: 3.8
A8: 2021 | B8: 1.48 | C8: 1.33 | D8: 0.8 | E8: 0.97 | F8: 4.58
A9: 2022 | B9: 1.37 | C9: 1.12 | D9: 1.03 | E9: 0.58 | F9: 4.1
A10: Grand Total | B10: 7.81 | C10: 4.39 | D10: 4.2 | E10: 4.22 | F10: 20.62

Sheet Sheet12
A3: Sum of Debt/Equity Ratio | B3: Column Labels
A4: Row Labels | B4: Hindalco | C4: Jindal Steel | D4: JSW Steel | E4: Tata Steel | F4: Grand Total
A5: 2018 | B5: 0.41 | C5: 0.94 | D5: 1.14 | E5: 0.41 | F5: 2.9
A6: 2019 | B6: 0.4 | C6: 0.78 | D6: 0.94 | E6: 0.38 | F6: 2.5
A7: 2020 | B7: 0.51 | C7: 0.64 | D7: 1.2 | E7: 0.53 | F7: 2.88
A8: 2021 | B8: 0.39 | C8: 0.51 | D8: 0.87 | E8: 0.34 | F8: 2.11
A9: 2022 | B9: 0.35 | C9: 0.33 | D9: 0.79 | E9: 0.26 | F9: 1.73
A10: Grand Total | B10: 2.06 | C10: 3.2 | D10: 4.94 | E10: 1.92 | F10: 12.12

Sheet Sheet13
A3: Sum of Interest Coverage Ratio | B3: Column Labels
A4: Row Labels | B4: Hindalco | C4: Jindal Steel | D4: JSW Steel | E4: Tata Steel | F4: Grand Total
A5: 2018 | B5: 2.34 | C5: 0.86 | D5: 3.04 | E5: 4.56 | F5: 10.8
A6: 2019 | B6: 2.08 | C6: 1.29 | D6: 4.09 | E6: 6.79 | F6: 14.25
A7: 2020 | B7: 1.61 | C7: 1.34 | D7: 2.39 | E7: 3.74 | F7: 9.08
A8: 2021 | B8: 3.23 | C8: 5.25 | D8: 4.53 | E8: 6.14 | F8: 19.15
A9: 2022 | B9: 8.28 | C9: 10.7 | D9: 8.78 | E9: 18.83 | F9: 46.59
A10: Grand Total | B10: 17.54 | C10: 19.44 | D10: 22.83 | E10: 40.06 | F10: 99.87

Sheet Sheet14
A3: Sum of Asset Turnover | B3: Column Labels
A4: Row Labels | B4: Hindalco | C4: Jindal Steel | D4: JSW Steel | E4: Tata Steel | F4: Grand Total
A5: 2018 | B5: 0.5174 | C5: 0.284 | D5: 0.7594 | E5: 0.4764 | F5: 2.0372
A6: 2019 | B6: 0.5613 | C6: 0.4805 | D6: 0.7185 | E6: 0.5135 | F6: 2.2738
A7: 2020 | B7: 0.5026 | C7: 0.4454 | D7: 0.5265 | E7: 0.4018 | F7: 1.8763
A8: 2021 | B8: 0.0051 | C8: 0.4818 | D8: 0.5308 | E8: 0.0051 | F8: 1.0228
A9: 2022 | B9: 0.0072 | C9: 0.0069 | D9: 0.008 | E9: 0.0064 | F9: 0.0285
A10: Grand Total | B10: 1.5936 | C10: 1.6986 | D10: 2.5432 | E10: 1.4032 | F10: 7.2386
